{"success":{"crystal":true,"holidays":true,"list":true,"queryDate":true,"serverTime":true,"serverTimestamp":true,"splitTotalBox":true,"splitTotalBoxInfo":true,"splitTotalBoxUnit":true,"splitTotalBoxUnitInfo":true,"totalBox":true,"totalBoxInfo":true,"totalBoxUnit":true,"totalBoxUnitInfo":true,"updateInfo":true},"data":{"crystal":{"status":0,"viewUnitInfo":"\u4e07\u5f20"},"holidays":"","list":[{"avgSeatView":"31.9%","avgShowView":"30","avgViewBox":"35.7","boxInfo":"6872.93","boxRate":"66.3%","movieId":78607,"movieName":"\u7ec8\u7ed3\u8005\uff1a\u521b\u4e16\u7eaa","myRefundNumInfo":"--","myRefundRateInfo":"--","onlineBoxRate":"63.5%","refundViewInfo":"--","refundViewRate":"--","releaseInfo":"\u4e0a\u66202\u5929","releaseInfoColor":"#666666 1.00","seatRate":"54.5%","showInfo":"64216","showRate":"41.8%","splitAvgViewBox":"35.7","splitBoxInfo":"6872.93","splitBoxRate":"66.3%","splitSumBoxInfo":"2.36\u4ebf","sumBoxInfo":"2.36\u4ebf","viewInfo":"192.4","viewInfoV2":"192.4\u4e07"},{"avgSeatView":"24.3%","avgShowView":"16","avgViewBox":"32.9","boxInfo":"1190.27","boxRate":"11.4%","movieId":246505,"movieName":"\u6eda\u86cb\u5427\uff01\u80bf\u7624\u541b","myRefundNumInfo":"--","myRefundRateInfo":"--","onlineBoxRate":"58.2%","refundViewInfo":"--","refundViewRate":"--","releaseInfo":"\u4e0a\u662012\u5929","releaseInfoColor":"#666666 1.00","seatRate":"13.4%","showInfo":"22798","showRate":"14.8%","splitAvgViewBox":"32.9","splitBoxInfo":"1190.27","splitBoxRate":"11.4%","splitSumBoxInfo":"4.34\u4ebf","sumBoxInfo":"4.34\u4ebf","viewInfo":"36.0","viewInfoV2":"36.0\u4e07"},{"avgSeatView":"15.5%","avgShowView":"10","avgViewBox":"32.8","boxInfo":"642.71","boxRate":"6.2%","movieId":246026,"movieName":"\u65b0\u5a18\u5927\u4f5c\u6218","myRefundNumInfo":"--","myRefundRateInfo":"--","onlineBoxRate":"47.5%","refundViewInfo":"--","refundViewRate":"--","releaseInfo":"\u4e0a\u66205\u5929","releaseInfoColor":"#666666 1.00","seatRate":"11.3%","showInfo":"21004","showRate":"13.6%","splitAvgViewBox":"32.8","splitBoxInfo":"642.71","splitBoxRate":"6.2%","splitSumBoxInfo":"1.57\u4ebf","sumBoxInfo":"1.57\u4ebf","viewInfo":"19.5","viewInfoV2":"19.5\u4e07"},{"avgSeatView":"22.7%","avgShowView":"14","avgViewBox":"34.9","boxInfo":"608.17","boxRate":"5.8%","movieId":246083,"movieName":"\u6349\u5996\u8bb0","myRefundNumInfo":"--","myRefundRateInfo":"--","onlineBoxRate":"45.2%","refundViewInfo":"--","refundViewRate":"--","releaseInfo":"\u4e0a\u662040\u5929","releaseInfoColor":"#666666 1.00","seatRate":"6.9%","showInfo":"12852","showRate":"8.3%","splitAvgViewBox":"34.9","splitBoxInfo":"608.17","splitBoxRate":"5.8%","splitSumBoxInfo":"23.38\u4ebf","sumBoxInfo":"23.38\u4ebf","viewInfo":"17.3","viewInfoV2":"17.3\u4e07"},{"avgSeatView":"18.2%","avgShowView":"11","avgViewBox":"31.6","boxInfo":"194.50","boxRate":"1.8%","movieId":246397,"movieName":"\u897f\u6e38\u8bb0\u4e4b\u5927\u5723\u5f52\u6765","myRefundNumInfo":"--","myRefundRateInfo":"--","onlineBoxRate":"52.1%","refundViewInfo":"--","refundViewRate":"--","releaseInfo":"\u4e0a\u662046\u5929","releaseInfoColor":"#666666 1.00","seatRate":"3.0%","showInfo":"5663","showRate":"3.6%","splitAvgViewBox":"31.6","splitBoxInfo":"194.50","splitBoxRate":"1.8%","splitSumBoxInfo":"9.39\u4ebf","sumBoxInfo":"9.39\u4ebf","viewInfo":"6.1","viewInfoV2":"6.1\u4e07"},{"avgSeatView":"100%","avgShowView":"64","avgViewBox":"54.1","boxInfo":"188.94","boxRate":"1.8%","movieId":341046,"movieName":"\u6218\u706b\u4e2d\u7684\u82ad\u857e","myRefundNumInfo":"--","myRefundRateInfo":"--","onlineBoxRate":"0.1%","refundViewInfo":"--","refundViewRate":"--","releaseInfo":"\u4e0a\u66204\u5929","releaseInfoColor":"#666666 1.00","seatRate":"0.2%","showInfo":"548","showRate":"0.3%","splitAvgViewBox":"54.1","splitBoxInfo":"188.94","splitBoxRate":"1.8%","splitSumBoxInfo":"786.0\u4e07","sumBoxInfo":"786.0\u4e07","viewInfo":"3.4","viewInfoV2":"3.4\u4e07"},{"avgSeatView":"18.9%","avgShowView":"10","avgViewBox":"33.1","boxInfo":"168.77","boxRate":"1.6%","movieId":248753,"movieName":"\u6d1b\u514b\u738b\u56fd4\uff1a\u51fa\u53d1\uff01\u5de8\u4eba\u8c37","myRefundNumInfo":"--","myRefundRateInfo":"--","onlineBoxRate":"50.9%","refundViewInfo":"--","refundViewRate":"--","releaseInfo":"\u4e0a\u662012\u5929","releaseInfoColor":"#666666 1.00","seatRate":"2.4%","showInfo":"5196","showRate":"3.3%","splitAvgViewBox":"33.1","splitBoxInfo":"168.77","splitBoxRate":"1.6%","splitSumBoxInfo":"6302.2\u4e07","sumBoxInfo":"6302.2\u4e07","viewInfo":"5.0","viewInfoV2":"5.0\u4e07"},{"avgSeatView":"9.6%","avgShowView":"5","avgViewBox":"35.1","boxInfo":"116.04","boxRate":"1.1%","movieId":246297,"movieName":"\u604b\u7231\u4e2d\u7684\u57ce\u5e02","myRefundNumInfo":"--","myRefundRateInfo":"--","onlineBoxRate":"50.5%","refundViewInfo":"--","refundViewRate":"--","releaseInfo":"\u4e0a\u66205\u5929","releaseInfoColor":"#666666 1.00","seatRate":"3.1%","showInfo":"7095","showRate":"4.6%","splitAvgViewBox":"35.1","splitBoxInfo":"116.04","splitBoxRate":"1.1%","splitSumBoxInfo":"5184.1\u4e07","sumBoxInfo":"5184.1\u4e07","viewInfo":"3.3","viewInfoV2":"3.3\u4e07"},{"avgSeatView":"23.2%","avgShowView":"9","avgViewBox":"35.4","boxInfo":"49.82","boxRate":"0.4%","movieId":246330,"movieName":"\u714e\u997c\u4fa0","myRefundNumInfo":"--","myRefundRateInfo":"--","onlineBoxRate":"44.6%","refundViewInfo":"--","refundViewRate":"--","releaseInfo":"\u4e0a\u662039\u5929","releaseInfoColor":"#666666 1.00","seatRate":"0.5%","showInfo":"1627","showRate":"1.0%","splitAvgViewBox":"35.4","splitBoxInfo":"49.82","splitBoxRate":"0.4%","splitSumBoxInfo":"11.58\u4ebf","sumBoxInfo":"11.58\u4ebf","viewInfo":"1.4","viewInfoV2":"1.4\u4e07"},{"avgSeatView":"100%","avgShowView":"132","avgViewBox":"35.0","boxInfo":"37.69","boxRate":"0.3%","movieId":341990,"movieName":"\u6211\u548c\u7ea2\u4e03\u519b","myRefundNumInfo":"--","myRefundRateInfo":"--","onlineBoxRate":"<0.1%","refundViewInfo":"--","refundViewRate":"--","releaseInfo":"2011-06","releaseInfoColor":"#666666 1.00","seatRate":"<0.1%","showInfo":"82","showRate":"<0.1%","splitAvgViewBox":"35.0","splitBoxInfo":"37.69","splitBoxRate":"0.3%","splitSumBoxInfo":"419.5\u4e07","sumBoxInfo":"419.5\u4e07","viewInfo":"1.0","viewInfoV2":"1.0\u4e07"},{"avgSeatView":"100%","avgShowView":"132","avgViewBox":"34.9","boxInfo":"37.62","boxRate":"0.3%","movieId":341991,"movieName":"\u9e6d\u8bed","myRefundNumInfo":"--","myRefundRateInfo":"--","onlineBoxRate":"<0.1%","refundViewInfo":"--","refundViewRate":"--","releaseInfo":"\u5c55\u6620","releaseInfoColor":"#666666 1.00","seatRate":"<0.1%","showInfo":"82","showRate":"<0.1%","splitAvgViewBox":"34.9","splitBoxInfo":"37.62","splitBoxRate":"0.3%","splitSumBoxInfo":"412.4\u4e07","sumBoxInfo":"412.4\u4e07","viewInfo":"1.0","viewInfoV2":"1.0\u4e07"},{"avgSeatView":"21.6%","avgShowView":"11","avgViewBox":"35.1","boxInfo":"34.15","boxRate":"0.3%","movieId":78892,"movieName":"\u7834\u98ce","myRefundNumInfo":"--","myRefundRateInfo":"--","onlineBoxRate":"70.7%","refundViewInfo":"--","refundViewRate":"--","releaseInfo":"\u4e0a\u662019\u5929","releaseInfoColor":"#666666 1.00","seatRate":"0.4%","showInfo":"897","showRate":"0.5%","splitAvgViewBox":"35.1","splitBoxInfo":"34.15","splitBoxRate":"0.3%","splitSumBoxInfo":"1.44\u4ebf","sumBoxInfo":"1.44\u4ebf","viewInfo":"0.9","viewInfoV2":"9712"},{"avgSeatView":"15.4%","avgShowView":"6","avgViewBox":"28.5","boxInfo":"31.55","boxRate":"0.3%","movieId":341598,"movieName":"\u53cc\u751f\u7075","myRefundNumInfo":"--","myRefundRateInfo":"--","onlineBoxRate":"46.6%","refundViewInfo":"--","refundViewRate":"--","releaseInfo":"\u4e0a\u66204\u5929","releaseInfoColor":"#666666 1.00","seatRate":"0.6%","showInfo":"1880","showRate":"1.2%","splitAvgViewBox":"28.5","splitBoxInfo":"31.55","splitBoxRate":"0.3%","splitSumBoxInfo":"216.4\u4e07","sumBoxInfo":"216.4\u4e07","viewInfo":"1.1","viewInfoV2":"1.1\u4e07"},{"avgSeatView":"13.5%","avgShowView":"7","avgViewBox":"30.0","boxInfo":"26.63","boxRate":"0.2%","movieId":248592,"movieName":"\u9ed1\u732b\u8b66\u957f\u4e4b\u7fe1\u7fe0\u4e4b\u661f","myRefundNumInfo":"--","myRefundRateInfo":"--","onlineBoxRate":"53.4%","refundViewInfo":"--","refundViewRate":"--","releaseInfo":"\u4e0a\u662018\u5929","releaseInfoColor":"#666666 1.00","seatRate":"0.5%","showInfo":"1472","showRate":"0.9%","splitAvgViewBox":"30.0","splitBoxInfo":"26.63","splitBoxRate":"0.2%","splitSumBoxInfo":"6401.8\u4e07","sumBoxInfo":"6401.8\u4e07","viewInfo":"0.8","viewInfoV2":"8861"},{"avgSeatView":"17.6%","avgShowView":"9","avgViewBox":"29.2","boxInfo":"26.15","boxRate":"0.2%","movieId":248463,"movieName":"\u6842\u5b9d\u4e4b\u7206\u7b11\u95ef\u5b87\u5b99","myRefundNumInfo":"--","myRefundRateInfo":"--","onlineBoxRate":"43.3%","refundViewInfo":"--","refundViewRate":"--","releaseInfo":"\u4e0a\u662019\u5929","releaseInfoColor":"#666666 1.00","seatRate":"0.4%","showInfo":"1092","showRate":"0.7%","splitAvgViewBox":"29.2","splitBoxInfo":"26.15","splitBoxRate":"0.2%","splitSumBoxInfo":"6256.2\u4e07","sumBoxInfo":"6256.2\u4e07","viewInfo":"0.8","viewInfoV2":"8957"},{"avgSeatView":"15.5%","avgShowView":"6","avgViewBox":"28.1","boxInfo":"20.18","boxRate":"0.1%","movieId":248551,"movieName":"\u767d\u96ea\u516c\u4e3b\u4e4b\u795e\u79d8\u7238\u7238","myRefundNumInfo":"--","myRefundRateInfo":"--","onlineBoxRate":"46.6%","refundViewInfo":"--","refundViewRate":"--","releaseInfo":"\u4e0a\u662011\u5929","releaseInfoColor":"#666666 1.00","seatRate":"0.4%","showInfo":"1225","showRate":"0.7%","splitAvgViewBox":"28.1","splitBoxInfo":"20.18","splitBoxRate":"0.1%","splitSumBoxInfo":"973.4\u4e07","sumBoxInfo":"973.4\u4e07","viewInfo":"0.7","viewInfoV2":"7170"},{"avgSeatView":"66.6%","avgShowView":"43","avgViewBox":"41.2","boxInfo":"18.28","boxRate":"0.1%","movieId":337611,"movieName":"\u9ed1\u77b3","myRefundNumInfo":"--","myRefundRateInfo":"--","onlineBoxRate":"0.3%","refundViewInfo":"--","refundViewRate":"--","releaseInfo":"\u4e0a\u662029\u5929","releaseInfoColor":"#666666 1.00","seatRate":"<0.1%","showInfo":"103","showRate":"<0.1%","splitAvgViewBox":"41.2","splitBoxInfo":"18.28","splitBoxRate":"0.1%","splitSumBoxInfo":"786.2\u4e07","sumBoxInfo":"786.2\u4e07","viewInfo":"0.4","viewInfoV2":"4429"},{"avgSeatView":"16.2%","avgShowView":"5","avgViewBox":"26.3","boxInfo":"17.82","boxRate":"0.1%","movieId":248968,"movieName":"\u4e03\u6708\u534a\u4e4b\u6050\u6016\u5bbf\u820d","myRefundNumInfo":"--","myRefundRateInfo":"--","onlineBoxRate":"35.7%","refundViewInfo":"--","refundViewRate":"--","releaseInfo":"\u4e0a\u662011\u5929","releaseInfoColor":"#666666 1.00","seatRate":"0.3%","showInfo":"1467","showRate":"0.9%","splitAvgViewBox":"26.3","splitBoxInfo":"17.82","splitBoxRate":"0.1%","splitSumBoxInfo":"1081.0\u4e07","sumBoxInfo":"1081.0\u4e07","viewInfo":"0.6","viewInfoV2":"6769"},{"avgSeatView":"--","avgShowView":"479","avgViewBox":"41.7","boxInfo":"10.00","boxRate":"<0.1%","movieId":78927,"movieName":"\u897f\u85cf\u5929\u7a7a","myRefundNumInfo":"--","myRefundRateInfo":"--","onlineBoxRate":"<0.1%","refundViewInfo":"--","refundViewRate":"--","releaseInfo":"2015-11","releaseInfoColor":"#666666 1.00","seatRate":"<0.1%","showInfo":"5","showRate":"<0.1%","splitAvgViewBox":"41.7","splitBoxInfo":"10.00","splitBoxRate":"<0.1%","splitSumBoxInfo":"1581.9\u4e07","sumBoxInfo":"1581.9\u4e07","viewInfo":"0.2","viewInfoV2":"2394"},{"avgSeatView":"3.5%","avgShowView":"2","avgViewBox":"27.8","boxInfo":"8.41","boxRate":"<0.1%","movieId":335035,"movieName":"\u738b\u5b50\u4e0e108\u715e","myRefundNumInfo":"--","myRefundRateInfo":"--","onlineBoxRate":"25.7%","refundViewInfo":"--","refundViewRate":"--","releaseInfo":"\u4e0a\u66204\u5929","releaseInfoColor":"#666666 1.00","seatRate":"0.7%","showInfo":"1663","showRate":"1.0%","splitAvgViewBox":"27.8","splitBoxInfo":"8.41","splitBoxRate":"<0.1%","splitSumBoxInfo":"131.4\u4e07","sumBoxInfo":"131.4\u4e07","viewInfo":"0.3","viewInfoV2":"3024"},{"avgSeatView":"100%","avgShowView":"166","avgViewBox":"39.2","boxInfo":"7.77","boxRate":"<0.1%","movieId":78690,"movieName":"\u4e09\u57ce\u8bb0","myRefundNumInfo":"--","myRefundRateInfo":"--","onlineBoxRate":"--","refundViewInfo":"--","refundViewRate":"--","releaseInfo":"\u70b9\u6620","releaseInfoColor":"#FF9900 1.00","seatRate":"<0.1%","showInfo":"12","showRate":"<0.1%","splitAvgViewBox":"39.2","splitBoxInfo":"7.77","splitBoxRate":"<0.1%","splitSumBoxInfo":"27.7\u4e07","sumBoxInfo":"27.7\u4e07","viewInfo":"0.1","viewInfoV2":"1982"},{"avgSeatView":"11.4%","avgShowView":"4","avgViewBox":"33.0","boxInfo":"6.64","boxRate":"<0.1%","movieId":246186,"movieName":"\u5b85\u5973\u4fa6\u63a2\u6842\u9999","myRefundNumInfo":"--","myRefundRateInfo":"--","onlineBoxRate":"<0.1%","refundViewInfo":"--","refundViewRate":"--","releaseInfo":"\u4e0a\u662012\u5929","releaseInfoColor":"#666666 1.00","seatRate":"0.1%","showInfo":"591","showRate":"0.3%","splitAvgViewBox":"33.0","splitBoxInfo":"6.64","splitBoxRate":"<0.1%","splitSumBoxInfo":"4110.8\u4e07","sumBoxInfo":"4110.8\u4e07","viewInfo":"0.2","viewInfoV2":"2014"},{"avgSeatView":"--","avgShowView":"54","avgViewBox":"39.1","boxInfo":"4.98","boxRate":"<0.1%","movieId":341368,"movieName":"\u738b\u5316\u4e70\u7236","myRefundNumInfo":"--","myRefundRateInfo":"--","onlineBoxRate":"--","refundViewInfo":"--","refundViewRate":"--","releaseInfo":"2014-09","releaseInfoColor":"#666666 1.00","seatRate":"<0.1%","showInfo":"24","showRate":"<0.1%","splitAvgViewBox":"39.1","splitBoxInfo":"4.98","splitBoxRate":"<0.1%","splitSumBoxInfo":"128.2\u4e07","sumBoxInfo":"128.2\u4e07","viewInfo":"0.1","viewInfoV2":"1274"},{"avgSeatView":"--","avgShowView":"44","avgViewBox":"35.5","boxInfo":"4.50","boxRate":"<0.1%","movieId":264152,"movieName":"\u674e\u4e09\u5a18","myRefundNumInfo":"--","myRefundRateInfo":"--","onlineBoxRate":"--","refundViewInfo":"--","refundViewRate":"--","releaseInfo":"\u5c55\u6620","releaseInfoColor":"#666666 1.00","seatRate":"<0.1%","showInfo":"29","showRate":"<0.1%","splitAvgViewBox":"35.5","splitBoxInfo":"4.50","splitBoxRate":"<0.1%","splitSumBoxInfo":"116.9\u4e07","sumBoxInfo":"116.9\u4e07","viewInfo":"0.1","viewInfoV2":"1265"},{"avgSeatView":"82.7%","avgShowView":"22","avgViewBox":"27.6","boxInfo":"1.83","boxRate":"<0.1%","movieId":248902,"movieName":"\u6211\u7238\u6bd4\u6211\u5c0f\u56db\u5c81","myRefundNumInfo":"--","myRefundRateInfo":"--","onlineBoxRate":"--","refundViewInfo":"--","refundViewRate":"--","releaseInfo":"\u4e0a\u662018\u5929","releaseInfoColor":"#666666 1.00","seatRate":"<0.1%","showInfo":"31","showRate":"<0.1%","splitAvgViewBox":"27.6","splitBoxInfo":"1.83","splitBoxRate":"<0.1%","splitSumBoxInfo":"300.8\u4e07","sumBoxInfo":"300.8\u4e07","viewInfo":"0.0","viewInfoV2":"661"},{"avgSeatView":"6.9%","avgShowView":"4","avgViewBox":"30.4","boxInfo":"1.46","boxRate":"<0.1%","movieId":246089,"movieName":"\u8c1c\u57ce","myRefundNumInfo":"--","myRefundRateInfo":"--","onlineBoxRate":"<0.1%","refundViewInfo":"--","refundViewRate":"--","releaseInfo":"\u4e0a\u662026\u5929","releaseInfoColor":"#666666 1.00","seatRate":"<0.1%","showInfo":"153","showRate":"<0.1%","splitAvgViewBox":"30.4","splitBoxInfo":"1.46","splitBoxRate":"<0.1%","splitSumBoxInfo":"1.48\u4ebf","sumBoxInfo":"1.48\u4ebf","viewInfo":"0.0","viewInfoV2":"480"},{"avgSeatView":"40.4%","avgShowView":"10","avgViewBox":"24.4","boxInfo":"1.37","boxRate":"<0.1%","movieId":248550,"movieName":"\u7f8e\u4eba\u9c7c\u4e4b\u6d77\u76d7\u6765\u88ad","myRefundNumInfo":"--","myRefundRateInfo":"--","onlineBoxRate":"--","refundViewInfo":"--","refundViewRate":"--","releaseInfo":"\u4e0a\u662025\u5929","releaseInfoColor":"#666666 1.00","seatRate":"<0.1%","showInfo":"60","showRate":"<0.1%","splitAvgViewBox":"24.4","splitBoxInfo":"1.37","splitBoxRate":"<0.1%","splitSumBoxInfo":"1723.6\u4e07","sumBoxInfo":"1723.6\u4e07","viewInfo":"0.0","viewInfoV2":"562"},{"avgSeatView":"--","avgShowView":"298","avgViewBox":"45.0","boxInfo":"1.34","boxRate":"<0.1%","movieId":246007,"movieName":"\u53ef\u7231\u7684\u4f60","myRefundNumInfo":"--","myRefundRateInfo":"--","onlineBoxRate":"--","refundViewInfo":"--","refundViewRate":"--","releaseInfo":"2015-03","releaseInfoColor":"#666666 1.00","seatRate":"<0.1%","showInfo":"1","showRate":"<0.1%","splitAvgViewBox":"45.0","splitBoxInfo":"1.34","splitBoxRate":"<0.1%","splitSumBoxInfo":"2192.7\u4e07","sumBoxInfo":"2192.7\u4e07","viewInfo":"0.0","viewInfoV2":"298"},{"avgSeatView":"100%","avgShowView":"106","avgViewBox":"41.8","boxInfo":"1.32","boxRate":"<0.1%","movieId":248233,"movieName":"\u4e1c\u5317\u504f\u5317","myRefundNumInfo":"--","myRefundRateInfo":"--","onlineBoxRate":"--","refundViewInfo":"--","refundViewRate":"--","releaseInfo":"2015-12","releaseInfoColor":"#666666 1.00","seatRate":"<0.1%","showInfo":"3","showRate":"<0.1%","splitAvgViewBox":"41.8","splitBoxInfo":"1.32","splitBoxRate":"<0.1%","splitSumBoxInfo":"2.3\u4e07","sumBoxInfo":"2.3\u4e07","viewInfo":"0.0","viewInfoV2":"316"},{"avgSeatView":"30.7%","avgShowView":"4","avgViewBox":"20.4","boxInfo":"1.29","boxRate":"<0.1%","movieId":341235,"movieName":"\u975e\u4f60\u52ff\u6270","myRefundNumInfo":"--","myRefundRateInfo":"--","onlineBoxRate":"--","refundViewInfo":"--","refundViewRate":"--","releaseInfo":"\u4e0a\u66205\u5929","releaseInfoColor":"#666666 1.00","seatRate":"<0.1%","showInfo":"182","showRate":"0.1%","splitAvgViewBox":"20.4","splitBoxInfo":"1.29","splitBoxRate":"<0.1%","splitSumBoxInfo":"32.5\u4e07","sumBoxInfo":"32.5\u4e07","viewInfo":"0.0","viewInfoV2":"635"},{"avgSeatView":"20.7%","avgShowView":"3","avgViewBox":"22.1","boxInfo":"1.27","boxRate":"<0.1%","movieId":341063,"movieName":"\u72c2\u91ce\u98de\u8f66","myRefundNumInfo":"--","myRefundRateInfo":"--","onlineBoxRate":"--","refundViewInfo":"--","refundViewRate":"--","releaseInfo":"\u4e0a\u662011\u5929","releaseInfoColor":"#666666 1.00","seatRate":"<0.1%","showInfo":"249","showRate":"0.1%","splitAvgViewBox":"22.1","splitBoxInfo":"1.27","splitBoxRate":"<0.1%","splitSumBoxInfo":"212.8\u4e07","sumBoxInfo":"212.8\u4e07","viewInfo":"0.0","viewInfoV2":"576"},{"avgSeatView":"100%","avgShowView":"41","avgViewBox":"36.5","boxInfo":"1.19","boxRate":"<0.1%","movieId":247681,"movieName":"\u9093\u5c0f\u5e73\u767b\u9ec4\u5c71","myRefundNumInfo":"--","myRefundRateInfo":"--","onlineBoxRate":"--","refundViewInfo":"--","refundViewRate":"--","releaseInfo":"2016-07","releaseInfoColor":"#666666 1.00","seatRate":"<0.1%","showInfo":"8","showRate":"<0.1%","splitAvgViewBox":"36.5","splitBoxInfo":"1.19","splitBoxRate":"<0.1%","splitSumBoxInfo":"127.2\u4e07","sumBoxInfo":"127.2\u4e07","viewInfo":"0.0","viewInfoV2":"327"},{"avgSeatView":"--","avgShowView":"100","avgViewBox":"35.8","boxInfo":"1.07","boxRate":"<0.1%","movieId":78267,"movieName":"\u4eac\u57ce81\u53f7","myRefundNumInfo":"--","myRefundRateInfo":"--","onlineBoxRate":"--","refundViewInfo":"--","refundViewRate":"--","releaseInfo":"2014-07","releaseInfoColor":"#666666 1.00","seatRate":"<0.1%","showInfo":"3","showRate":"<0.1%","splitAvgViewBox":"35.8","splitBoxInfo":"1.07","splitBoxRate":"<0.1%","splitSumBoxInfo":"4.11\u4ebf","sumBoxInfo":"4.11\u4ebf","viewInfo":"0.0","viewInfoV2":"300"},{"avgSeatView":"--","avgShowView":"8","avgViewBox":"47.3","boxInfo":"1.06","boxRate":"<0.1%","movieId":341346,"movieName":"\u7b49\u7231\u5f52\u6765","myRefundNumInfo":"--","myRefundRateInfo":"--","onlineBoxRate":"--","refundViewInfo":"--","refundViewRate":"--","releaseInfo":"\u4e0a\u662028\u5929","releaseInfoColor":"#666666 1.00","seatRate":"<0.1%","showInfo":"30","showRate":"<0.1%","splitAvgViewBox":"47.3","splitBoxInfo":"1.06","splitBoxRate":"<0.1%","splitSumBoxInfo":"68.1\u4e07","sumBoxInfo":"68.1\u4e07","viewInfo":"0.0","viewInfoV2":"224"}],"queryDate":"2015-08-24","serverTime":"2020-03-14 00:31:32","serverTimestamp":1584117092000,"splitTotalBox":"10356.5","splitTotalBoxInfo":"10356.5","splitTotalBoxUnit":"\u4e07","splitTotalBoxUnitInfo":"\u4e07","totalBox":"10356.5","totalBoxInfo":"10356.5","totalBoxUnit":"\u4e07","totalBoxUnitInfo":"\u4e07","updateInfo":"\u5317\u4eac\u65f6\u95f4\u6bcf\u592912\u70b9\u66f4\u65b0\u7968\u623f"},"status":{"crystal":200,"holidays":200,"list":200,"queryDate":200,"serverTime":200,"serverTimestamp":200,"splitTotalBox":200,"splitTotalBoxInfo":200,"splitTotalBoxUnit":200,"splitTotalBoxUnitInfo":200,"totalBox":200,"totalBoxInfo":200,"totalBoxUnit":200,"totalBoxUnitInfo":200,"updateInfo":200}}