{"success":{"crystal":true,"holidays":true,"list":true,"queryDate":true,"serverTime":true,"serverTimestamp":true,"splitTotalBox":true,"splitTotalBoxInfo":true,"splitTotalBoxUnit":true,"splitTotalBoxUnitInfo":true,"totalBox":true,"totalBoxInfo":true,"totalBoxUnit":true,"totalBoxUnitInfo":true,"updateInfo":true},"data":{"crystal":{"status":0,"viewUnitInfo":"\u4e07\u5f20"},"holidays":"","list":[{"avgSeatView":"31.9%","avgShowView":"46","avgViewBox":"36.7","boxInfo":"7482.05","boxRate":"25.9%","movieId":248700,"movieName":"\u901f\u5ea6\u4e0e\u6fc0\u60c58","myRefundNumInfo":"1.6\u4e07","myRefundRateInfo":"2.5%","onlineBoxRate":"78.7%","refundViewInfo":"3.0\u4e07","refundViewRate":"1.4%","releaseInfo":"\u4e0a\u662017\u5929","releaseInfoColor":"#666666 1.00","seatRate":"19.7%","showInfo":"44874","showRate":"16.7%","splitAvgViewBox":"34.5","splitBoxInfo":"7040.02","splitBoxRate":"25.8%","splitSumBoxInfo":"23.50\u4ebf","sumBoxInfo":"24.91\u4ebf","viewInfo":"203.7","viewInfoV2":"203.7\u4e07"},{"avgSeatView":"27.8%","avgShowView":"36","avgViewBox":"32.6","boxInfo":"6871.86","boxRate":"23.7%","movieId":346103,"movieName":"\u62c6\u5f39\u00b7\u4e13\u5bb6","myRefundNumInfo":"1.3\u4e07","myRefundRateInfo":"2.1%","onlineBoxRate":"81.5%","refundViewInfo":"2.7\u4e07","refundViewRate":"1.2%","releaseInfo":"\u4e0a\u66203\u5929","releaseInfoColor":"#666666 1.00","seatRate":"23.4%","showInfo":"58911","showRate":"21.9%","splitAvgViewBox":"30.4","splitBoxInfo":"6408.04","splitBoxRate":"23.5%","splitSumBoxInfo":"1.68\u4ebf","sumBoxInfo":"1.81\u4ebf","viewInfo":"210.3","viewInfoV2":"210.3\u4e07"},{"avgSeatView":"21.3%","avgShowView":"29","avgViewBox":"35.1","boxInfo":"5433.42","boxRate":"18.8%","movieId":345672,"movieName":"\u8bb0\u5fc6\u5927\u5e08","myRefundNumInfo":"1.4\u4e07","myRefundRateInfo":"2.5%","onlineBoxRate":"83.6%","refundViewInfo":"2.4\u4e07","refundViewRate":"1.5%","releaseInfo":"\u4e0a\u66203\u5929","releaseInfoColor":"#666666 1.00","seatRate":"22.5%","showInfo":"54878","showRate":"20.4%","splitAvgViewBox":"33.4","splitBoxInfo":"5184.08","splitBoxRate":"19.0%","splitSumBoxInfo":"1.51\u4ebf","sumBoxInfo":"1.57\u4ebf","viewInfo":"154.7","viewInfoV2":"154.7\u4e07"},{"avgSeatView":"24.9%","avgShowView":"27","avgViewBox":"34.6","boxInfo":"3233.45","boxRate":"11.1%","movieId":672175,"movieName":"\u559c\u6b22\u00b7\u4f60","myRefundNumInfo":"9656","myRefundRateInfo":"2.7%","onlineBoxRate":"86.9%","refundViewInfo":"1.5\u4e07","refundViewRate":"1.5%","releaseInfo":"\u4e0a\u66204\u5929","releaseInfoColor":"#666666 1.00","seatRate":"11.6%","showInfo":"35912","showRate":"13.3%","splitAvgViewBox":"32.8","splitBoxInfo":"3072.00","splitBoxRate":"11.2%","splitSumBoxInfo":"1.15\u4ebf","sumBoxInfo":"1.22\u4ebf","viewInfo":"93.4","viewInfoV2":"93.4\u4e07"},{"avgSeatView":"21.7%","avgShowView":"24","avgViewBox":"36.0","boxInfo":"2886.54","boxRate":"9.9%","movieId":672114,"movieName":"\u6625\u5a07\u6551\u5fd7\u660e","myRefundNumInfo":"1.1\u4e07","myRefundRateInfo":"3.4%","onlineBoxRate":"89.5%","refundViewInfo":"1.6\u4e07","refundViewRate":"2.0%","releaseInfo":"\u4e0a\u66203\u5929","releaseInfoColor":"#666666 1.00","seatRate":"11.4%","showInfo":"33535","showRate":"12.4%","splitAvgViewBox":"34.0","splitBoxInfo":"2730.50","splitBoxRate":"10.0%","splitSumBoxInfo":"9244.1\u4e07","sumBoxInfo":"9709.0\u4e07","viewInfo":"80.1","viewInfoV2":"80.1\u4e07"},{"avgSeatView":"29.3%","avgShowView":"31","avgViewBox":"33.2","boxInfo":"1876.24","boxRate":"6.4%","movieId":78610,"movieName":"\u84dd\u7cbe\u7075\uff1a\u5bfb\u627e\u795e\u79d8\u6751","myRefundNumInfo":"4048","myRefundRateInfo":"2.2%","onlineBoxRate":"72.8%","refundViewInfo":"7555","refundViewRate":"1.3%","releaseInfo":"\u4e0a\u662010\u5929","releaseInfoColor":"#666666 1.00","seatRate":"5.9%","showInfo":"18608","showRate":"6.9%","splitAvgViewBox":"31.2","splitBoxInfo":"1764.29","splitBoxRate":"6.4%","splitSumBoxInfo":"1.18\u4ebf","sumBoxInfo":"1.25\u4ebf","viewInfo":"56.4","viewInfoV2":"56.4\u4e07"},{"avgSeatView":"30.7%","avgShowView":"27","avgViewBox":"28.2","boxInfo":"380.71","boxRate":"1.3%","movieId":343669,"movieName":"\u50b2\u5a07\u4e0e\u504f\u89c1","myRefundNumInfo":"1806","myRefundRateInfo":"2.9%","onlineBoxRate":"85.8%","refundViewInfo":"2580","refundViewRate":"1.8%","releaseInfo":"\u4e0a\u662011\u5929","releaseInfoColor":"#666666 1.00","seatRate":"1.3%","showInfo":"5066","showRate":"1.8%","splitAvgViewBox":"26.4","splitBoxInfo":"356.04","splitBoxRate":"1.3%","splitSumBoxInfo":"1.06\u4ebf","sumBoxInfo":"1.14\u4ebf","viewInfo":"13.4","viewInfoV2":"13.4\u4e07"},{"avgSeatView":"17.0%","avgShowView":"16","avgViewBox":"30.8","boxInfo":"289.73","boxRate":"1.0%","movieId":544704,"movieName":"\u7075\u72fc\u4f20\u5947","myRefundNumInfo":"647","myRefundRateInfo":"2.1%","onlineBoxRate":"68.8%","refundViewInfo":"1398","refundViewRate":"1.4%","releaseInfo":"\u4e0a\u66202\u5929","releaseInfoColor":"#666666 1.00","seatRate":"1.7%","showInfo":"5990","showRate":"2.2%","splitAvgViewBox":"28.9","splitBoxInfo":"272.21","splitBoxRate":"0.9%","splitSumBoxInfo":"526.9\u4e07","sumBoxInfo":"558.7\u4e07","viewInfo":"9.3","viewInfoV2":"9.3\u4e07"},{"avgSeatView":"16.5%","avgShowView":"11","avgViewBox":"24.0","boxInfo":"149.91","boxRate":"0.5%","movieId":1201660,"movieName":"\u8840\u72fc\u72ac","myRefundNumInfo":"115","myRefundRateInfo":"3.8%","onlineBoxRate":"34.9%","refundViewInfo":"849","refundViewRate":"1.3%","releaseInfo":"\u4e0a\u662010\u5929","releaseInfoColor":"#666666 1.00","seatRate":"1.1%","showInfo":"5771","showRate":"2.1%","splitAvgViewBox":"23.7","splitBoxInfo":"148.00","splitBoxRate":"0.5%","splitSumBoxInfo":"2068.8\u4e07","sumBoxInfo":"2102.2\u4e07","viewInfo":"6.2","viewInfoV2":"6.2\u4e07"},{"avgSeatView":"21.0%","avgShowView":"16","avgViewBox":"27.3","boxInfo":"45.58","boxRate":"0.1%","movieId":158,"movieName":"\u5927\u8bdd\u897f\u6e38\u4e4b\u5927\u5723\u5a36\u4eb2","myRefundNumInfo":"--","myRefundRateInfo":"--","onlineBoxRate":"83.0%","refundViewInfo":"341","refundViewRate":"2.0%","releaseInfo":"\u91cd\u662018\u5929","releaseInfoColor":"#666666 1.00","seatRate":"0.2%","showInfo":"1055","showRate":"0.3%","splitAvgViewBox":"24.9","splitBoxInfo":"41.65","splitBoxRate":"0.1%","splitSumBoxInfo":"1.62\u4ebf","sumBoxInfo":"1.76\u4ebf","viewInfo":"1.6","viewInfoV2":"1.6\u4e07"},{"avgSeatView":"73.0%","avgShowView":"84","avgViewBox":"37.8","boxInfo":"32.58","boxRate":"0.1%","movieId":588362,"movieName":"\u6454\u8de4\u5427\uff01\u7238\u7238","myRefundNumInfo":"--","myRefundRateInfo":"--","onlineBoxRate":"88.8%","refundViewInfo":"--","refundViewRate":"--","releaseInfo":"\u70b9\u6620","releaseInfoColor":"#FF9900 1.00","seatRate":"<0.1%","showInfo":"103","showRate":"<0.1%","splitAvgViewBox":"35.5","splitBoxInfo":"30.59","splitBoxRate":"0.1%","splitSumBoxInfo":"30.5\u4e07","sumBoxInfo":"32.5\u4e07","viewInfo":"0.8","viewInfoV2":"8616"},{"avgSeatView":"11.6%","avgShowView":"9","avgViewBox":"25.3","boxInfo":"29.55","boxRate":"0.1%","movieId":1196172,"movieName":"\u5348\u591c\u60ca\u9b42\u8def","myRefundNumInfo":"166","myRefundRateInfo":"3.8%","onlineBoxRate":"--","refundViewInfo":"246","refundViewRate":"2.0%","releaseInfo":"\u4e0a\u66203\u5929","releaseInfoColor":"#666666 1.00","seatRate":"0.3%","showInfo":"1339","showRate":"0.4%","splitAvgViewBox":"23.2","splitBoxInfo":"27.20","splitBoxRate":"<0.1%","splitSumBoxInfo":"86.1\u4e07","sumBoxInfo":"93.3\u4e07","viewInfo":"1.1","viewInfoV2":"1.1\u4e07"},{"avgSeatView":"29.4%","avgShowView":"23","avgViewBox":"28.1","boxInfo":"11.23","boxRate":"<0.1%","movieId":1200610,"movieName":"\u7aa6\u5a25\u5947\u51a4","myRefundNumInfo":"5","myRefundRateInfo":"2.9%","onlineBoxRate":"5.3%","refundViewInfo":"46","refundViewRate":"1.1%","releaseInfo":"\u4e0a\u662010\u5929","releaseInfoColor":"#666666 1.00","seatRate":"<0.1%","showInfo":"178","showRate":"<0.1%","splitAvgViewBox":"27.9","splitBoxInfo":"11.16","splitBoxRate":"<0.1%","splitSumBoxInfo":"390.7\u4e07","sumBoxInfo":"395.1\u4e07","viewInfo":"0.3","viewInfoV2":"3993"},{"avgSeatView":"19.2%","avgShowView":"16","avgViewBox":"41.0","boxInfo":"10.97","boxRate":"<0.1%","movieId":246969,"movieName":"\u653b\u58f3\u673a\u52a8\u961f","myRefundNumInfo":"14","myRefundRateInfo":"2.1%","onlineBoxRate":"78.4%","refundViewInfo":"20","refundViewRate":"0.7%","releaseInfo":"\u4e0a\u662024\u5929","releaseInfoColor":"#666666 1.00","seatRate":"<0.1%","showInfo":"169","showRate":"<0.1%","splitAvgViewBox":"38.5","splitBoxInfo":"10.30","splitBoxRate":"<0.1%","splitSumBoxInfo":"1.90\u4ebf","sumBoxInfo":"2.02\u4ebf","viewInfo":"0.2","viewInfoV2":"2674"},{"avgSeatView":"97.9%","avgShowView":"107","avgViewBox":"30.0","boxInfo":"7.37","boxRate":"<0.1%","movieId":246307,"movieName":"\u7edd\u5730\u9003\u4ea1","myRefundNumInfo":"--","myRefundRateInfo":"--","onlineBoxRate":"<0.1%","refundViewInfo":"0","refundViewRate":"<0.1%","releaseInfo":"2016-07","releaseInfoColor":"#666666 1.00","seatRate":"<0.1%","showInfo":"23","showRate":"<0.1%","splitAvgViewBox":"30.0","splitBoxInfo":"7.37","splitBoxRate":"<0.1%","splitSumBoxInfo":"8.87\u4ebf","sumBoxInfo":"8.87\u4ebf","viewInfo":"0.2","viewInfoV2":"2455"},{"avgSeatView":"100%","avgShowView":"106","avgViewBox":"29.3","boxInfo":"6.84","boxRate":"<0.1%","movieId":79203,"movieName":"\u76d7\u5893\u7b14\u8bb0","myRefundNumInfo":"--","myRefundRateInfo":"--","onlineBoxRate":"<0.1%","refundViewInfo":"0","refundViewRate":"<0.1%","releaseInfo":"2016-08","releaseInfoColor":"#666666 1.00","seatRate":"<0.1%","showInfo":"22","showRate":"<0.1%","splitAvgViewBox":"29.3","splitBoxInfo":"6.84","splitBoxRate":"<0.1%","splitSumBoxInfo":"10.02\u4ebf","sumBoxInfo":"10.02\u4ebf","viewInfo":"0.2","viewInfoV2":"2330"},{"avgSeatView":"97.6%","avgShowView":"90","avgViewBox":"28.9","boxInfo":"6.46","boxRate":"<0.1%","movieId":78421,"movieName":"\u9b54\u517d","myRefundNumInfo":"--","myRefundRateInfo":"--","onlineBoxRate":"<0.1%","refundViewInfo":"2","refundViewRate":"<0.1%","releaseInfo":"2016-06","releaseInfoColor":"#666666 1.00","seatRate":"<0.1%","showInfo":"25","showRate":"<0.1%","splitAvgViewBox":"28.9","splitBoxInfo":"6.46","splitBoxRate":"<0.1%","splitSumBoxInfo":"14.68\u4ebf","sumBoxInfo":"14.68\u4ebf","viewInfo":"0.2","viewInfoV2":"2235"},{"avgSeatView":"95.6%","avgShowView":"99","avgViewBox":"30.8","boxInfo":"5.46","boxRate":"<0.1%","movieId":246234,"movieName":"\u7f8e\u56fd\u961f\u957f3","myRefundNumInfo":"--","myRefundRateInfo":"--","onlineBoxRate":"<0.1%","refundViewInfo":"4","refundViewRate":"0.2%","releaseInfo":"2016-05","releaseInfoColor":"#666666 1.00","seatRate":"<0.1%","showInfo":"18","showRate":"<0.1%","splitAvgViewBox":"30.8","splitBoxInfo":"5.46","splitBoxRate":"<0.1%","splitSumBoxInfo":"12.11\u4ebf","sumBoxInfo":"12.11\u4ebf","viewInfo":"0.1","viewInfoV2":"1772"},{"avgSeatView":"19.3%","avgShowView":"16","avgViewBox":"34.9","boxInfo":"4.65","boxRate":"<0.1%","movieId":249898,"movieName":"\u91d1\u521a\uff1a\u9ab7\u9ac5\u5c9b","myRefundNumInfo":"20","myRefundRateInfo":"4.6%","onlineBoxRate":"--","refundViewInfo":"27","refundViewRate":"1.9%","releaseInfo":"\u4e0a\u662038\u5929","releaseInfoColor":"#666666 1.00","seatRate":"<0.1%","showInfo":"85","showRate":"<0.1%","splitAvgViewBox":"32.3","splitBoxInfo":"4.31","splitBoxRate":"<0.1%","splitSumBoxInfo":"10.94\u4ebf","sumBoxInfo":"11.58\u4ebf","viewInfo":"0.1","viewInfoV2":"1333"},{"avgSeatView":"55.8%","avgShowView":"55","avgViewBox":"28.4","boxInfo":"4.62","boxRate":"<0.1%","movieId":1197558,"movieName":"\u732a\u732a\u4fa0\u4e4b\u82f1\u96c4\u732a\u5c11\u5e74","myRefundNumInfo":"3","myRefundRateInfo":"3.0%","onlineBoxRate":"6.2%","refundViewInfo":"3","refundViewRate":"0.1%","releaseInfo":"2017-01","releaseInfoColor":"#666666 1.00","seatRate":"<0.1%","showInfo":"30","showRate":"<0.1%","splitAvgViewBox":"28.2","splitBoxInfo":"4.58","splitBoxRate":"<0.1%","splitSumBoxInfo":"4215.9\u4e07","sumBoxInfo":"4467.8\u4e07","viewInfo":"0.1","viewInfoV2":"1626"},{"avgSeatView":"100%","avgShowView":"98","avgViewBox":"30.1","boxInfo":"4.42","boxRate":"<0.1%","movieId":341289,"movieName":"\u5bd2\u62182","myRefundNumInfo":"--","myRefundRateInfo":"--","onlineBoxRate":"<0.1%","refundViewInfo":"0","refundViewRate":"<0.1%","releaseInfo":"2016-07","releaseInfoColor":"#666666 1.00","seatRate":"<0.1%","showInfo":"15","showRate":"<0.1%","splitAvgViewBox":"30.1","splitBoxInfo":"4.42","splitBoxRate":"<0.1%","splitSumBoxInfo":"6.76\u4ebf","sumBoxInfo":"6.76\u4ebf","viewInfo":"0.1","viewInfoV2":"1470"},{"avgSeatView":"100.0%","avgShowView":"104","avgViewBox":"29.8","boxInfo":"4.34","boxRate":"<0.1%","movieId":246177,"movieName":"X\u6218\u8b66\uff1a\u5929\u542f","myRefundNumInfo":"--","myRefundRateInfo":"--","onlineBoxRate":"--","refundViewInfo":"0","refundViewRate":"<0.1%","releaseInfo":"2016-06","releaseInfoColor":"#666666 1.00","seatRate":"<0.1%","showInfo":"14","showRate":"<0.1%","splitAvgViewBox":"29.8","splitBoxInfo":"4.34","splitBoxRate":"<0.1%","splitSumBoxInfo":"8.00\u4ebf","sumBoxInfo":"8.00\u4ebf","viewInfo":"0.1","viewInfoV2":"1456"},{"avgSeatView":"96.8%","avgShowView":"90","avgViewBox":"29.7","boxInfo":"3.98","boxRate":"<0.1%","movieId":246267,"movieName":"\u957f\u57ce","myRefundNumInfo":"--","myRefundRateInfo":"--","onlineBoxRate":"--","refundViewInfo":"0","refundViewRate":"<0.1%","releaseInfo":"2016-12","releaseInfoColor":"#666666 1.00","seatRate":"<0.1%","showInfo":"15","showRate":"<0.1%","splitAvgViewBox":"29.7","splitBoxInfo":"3.98","splitBoxRate":"<0.1%","splitSumBoxInfo":"11.64\u4ebf","sumBoxInfo":"11.72\u4ebf","viewInfo":"0.1","viewInfoV2":"1340"},{"avgSeatView":"32.0%","avgShowView":"24","avgViewBox":"32.9","boxInfo":"3.63","boxRate":"<0.1%","movieId":342858,"movieName":"\u4e00\u6761\u72d7\u7684\u4f7f\u547d","myRefundNumInfo":"5","myRefundRateInfo":"1.6%","onlineBoxRate":"--","refundViewInfo":"8","refundViewRate":"0.7%","releaseInfo":"\u4e0a\u662059\u5929","releaseInfoColor":"#666666 1.00","seatRate":"<0.1%","showInfo":"46","showRate":"<0.1%","splitAvgViewBox":"30.5","splitBoxInfo":"3.37","splitBoxRate":"<0.1%","splitSumBoxInfo":"5.58\u4ebf","sumBoxInfo":"6.06\u4ebf","viewInfo":"0.1","viewInfoV2":"1104"},{"avgSeatView":"90.8%","avgShowView":"64","avgViewBox":"30.4","boxInfo":"3.49","boxRate":"<0.1%","movieId":247259,"movieName":"\u5927\u8bdd\u897f\u6e383","myRefundNumInfo":"--","myRefundRateInfo":"--","onlineBoxRate":"--","refundViewInfo":"0","refundViewRate":"<0.1%","releaseInfo":"2016-09","releaseInfoColor":"#666666 1.00","seatRate":"<0.1%","showInfo":"18","showRate":"<0.1%","splitAvgViewBox":"30.4","splitBoxInfo":"3.49","splitBoxRate":"<0.1%","splitSumBoxInfo":"3.65\u4ebf","sumBoxInfo":"3.65\u4ebf","viewInfo":"0.1","viewInfoV2":"1148"},{"avgSeatView":"94.2%","avgShowView":"103","avgViewBox":"30.5","boxInfo":"3.45","boxRate":"<0.1%","movieId":246188,"movieName":"\u6124\u6012\u7684\u5c0f\u9e1f","myRefundNumInfo":"--","myRefundRateInfo":"--","onlineBoxRate":"--","refundViewInfo":"0","refundViewRate":"<0.1%","releaseInfo":"2016-05","releaseInfoColor":"#666666 1.00","seatRate":"<0.1%","showInfo":"11","showRate":"<0.1%","splitAvgViewBox":"30.5","splitBoxInfo":"3.45","splitBoxRate":"<0.1%","splitSumBoxInfo":"5.12\u4ebf","sumBoxInfo":"5.12\u4ebf","viewInfo":"0.1","viewInfoV2":"1130"},{"avgSeatView":"100%","avgShowView":"82","avgViewBox":"49.2","boxInfo":"3.20","boxRate":"<0.1%","movieId":264152,"movieName":"\u674e\u4e09\u5a18","myRefundNumInfo":"--","myRefundRateInfo":"--","onlineBoxRate":"--","refundViewInfo":"0","refundViewRate":"<0.1%","releaseInfo":"\u5c55\u6620","releaseInfoColor":"#666666 1.00","seatRate":"<0.1%","showInfo":"8","showRate":"<0.1%","splitAvgViewBox":"49.2","splitBoxInfo":"3.20","splitBoxRate":"<0.1%","splitSumBoxInfo":"804.5\u4e07","sumBoxInfo":"804.5\u4e07","viewInfo":"0.0","viewInfoV2":"650"},{"avgSeatView":"98.8%","avgShowView":"108","avgViewBox":"29.6","boxInfo":"3.19","boxRate":"<0.1%","movieId":338506,"movieName":"\u8d4f\u91d1\u730e\u4eba","myRefundNumInfo":"--","myRefundRateInfo":"--","onlineBoxRate":"--","refundViewInfo":"0","refundViewRate":"<0.1%","releaseInfo":"2016-07","releaseInfoColor":"#666666 1.00","seatRate":"<0.1%","showInfo":"10","showRate":"<0.1%","splitAvgViewBox":"29.6","splitBoxInfo":"3.19","splitBoxRate":"<0.1%","splitSumBoxInfo":"2.13\u4ebf","sumBoxInfo":"2.13\u4ebf","viewInfo":"0.1","viewInfoV2":"1077"},{"avgSeatView":"94.0%","avgShowView":"103","avgViewBox":"29.6","boxInfo":"3.03","boxRate":"<0.1%","movieId":246333,"movieName":"\u60ca\u5929\u9b54\u76d7\u56e22","myRefundNumInfo":"--","myRefundRateInfo":"--","onlineBoxRate":"--","refundViewInfo":"0","refundViewRate":"<0.1%","releaseInfo":"2016-06","releaseInfoColor":"#666666 1.00","seatRate":"<0.1%","showInfo":"10","showRate":"<0.1%","splitAvgViewBox":"29.6","splitBoxInfo":"3.03","splitBoxRate":"<0.1%","splitSumBoxInfo":"6.37\u4ebf","sumBoxInfo":"6.37\u4ebf","viewInfo":"0.1","viewInfoV2":"1025"},{"avgSeatView":"97.7%","avgShowView":"102","avgViewBox":"32.2","boxInfo":"2.94","boxRate":"<0.1%","movieId":246970,"movieName":"\u5947\u5e7b\u68ee\u6797","myRefundNumInfo":"--","myRefundRateInfo":"--","onlineBoxRate":"--","refundViewInfo":"0","refundViewRate":"<0.1%","releaseInfo":"2016-04","releaseInfoColor":"#666666 1.00","seatRate":"<0.1%","showInfo":"9","showRate":"<0.1%","splitAvgViewBox":"32.2","splitBoxInfo":"2.94","splitBoxRate":"<0.1%","splitSumBoxInfo":"9.76\u4ebf","sumBoxInfo":"9.76\u4ebf","viewInfo":"0.0","viewInfoV2":"915"},{"avgSeatView":"72.2%","avgShowView":"28","avgViewBox":"11.8","boxInfo":"2.90","boxRate":"<0.1%","movieId":342906,"movieName":"\u975e\u51e1\u4efb\u52a1","myRefundNumInfo":"0","myRefundRateInfo":"<0.1%","onlineBoxRate":"--","refundViewInfo":"0","refundViewRate":"<0.1%","releaseInfo":"\u4e0a\u662031\u5929","releaseInfoColor":"#666666 1.00","seatRate":"<0.1%","showInfo":"90","showRate":"<0.1%","splitAvgViewBox":"11.8","splitBoxInfo":"2.88","splitBoxRate":"<0.1%","splitSumBoxInfo":"1.47\u4ebf","sumBoxInfo":"1.56\u4ebf","viewInfo":"0.2","viewInfoV2":"2444"},{"avgSeatView":"91.2%","avgShowView":"95","avgViewBox":"30.1","boxInfo":"2.86","boxRate":"<0.1%","movieId":247186,"movieName":"\u5c01\u795e\u4f20\u5947","myRefundNumInfo":"--","myRefundRateInfo":"--","onlineBoxRate":"--","refundViewInfo":"0","refundViewRate":"<0.1%","releaseInfo":"2016-07","releaseInfoColor":"#666666 1.00","seatRate":"<0.1%","showInfo":"10","showRate":"<0.1%","splitAvgViewBox":"30.1","splitBoxInfo":"2.86","splitBoxRate":"<0.1%","splitSumBoxInfo":"2.83\u4ebf","sumBoxInfo":"2.83\u4ebf","viewInfo":"0.0","viewInfoV2":"949"},{"avgSeatView":"100.0%","avgShowView":"104","avgViewBox":"30.0","boxInfo":"2.80","boxRate":"<0.1%","movieId":248916,"movieName":"\u94c1\u9053\u98de\u864e","myRefundNumInfo":"--","myRefundRateInfo":"--","onlineBoxRate":"--","refundViewInfo":"0","refundViewRate":"<0.1%","releaseInfo":"2016-12","releaseInfoColor":"#666666 1.00","seatRate":"<0.1%","showInfo":"9","showRate":"<0.1%","splitAvgViewBox":"30.0","splitBoxInfo":"2.80","splitBoxRate":"<0.1%","splitSumBoxInfo":"6.84\u4ebf","sumBoxInfo":"6.98\u4ebf","viewInfo":"0.0","viewInfoV2":"936"},{"avgSeatView":"97.9%","avgShowView":"87","avgViewBox":"30.7","boxInfo":"2.64","boxRate":"<0.1%","movieId":338443,"movieName":"\u673a\u68b0\u5e082\uff1a\u590d\u6d3b","myRefundNumInfo":"--","myRefundRateInfo":"--","onlineBoxRate":"--","refundViewInfo":"88","refundViewRate":"9.2%","releaseInfo":"2016-10","releaseInfoColor":"#666666 1.00","seatRate":"<0.1%","showInfo":"10","showRate":"<0.1%","splitAvgViewBox":"30.7","splitBoxInfo":"2.64","splitBoxRate":"<0.1%","splitSumBoxInfo":"3.38\u4ebf","sumBoxInfo":"3.38\u4ebf","viewInfo":"0.0","viewInfoV2":"862"},{"avgSeatView":"93.2%","avgShowView":"95","avgViewBox":"29.9","boxInfo":"2.53","boxRate":"<0.1%","movieId":248616,"movieName":"\u7235\u8ff9","myRefundNumInfo":"--","myRefundRateInfo":"--","onlineBoxRate":"--","refundViewInfo":"104","refundViewRate":"10.9%","releaseInfo":"2016-09","releaseInfoColor":"#666666 1.00","seatRate":"<0.1%","showInfo":"9","showRate":"<0.1%","splitAvgViewBox":"29.9","splitBoxInfo":"2.53","splitBoxRate":"<0.1%","splitSumBoxInfo":"3.82\u4ebf","sumBoxInfo":"3.82\u4ebf","viewInfo":"0.0","viewInfoV2":"847"},{"avgSeatView":"93.4%","avgShowView":"83","avgViewBox":"30.2","boxInfo":"2.49","boxRate":"<0.1%","movieId":246124,"movieName":"\u5947\u5f02\u535a\u58eb","myRefundNumInfo":"--","myRefundRateInfo":"--","onlineBoxRate":"--","refundViewInfo":"0","refundViewRate":"<0.1%","releaseInfo":"2016-11","releaseInfoColor":"#666666 1.00","seatRate":"<0.1%","showInfo":"10","showRate":"<0.1%","splitAvgViewBox":"30.2","splitBoxInfo":"2.49","splitBoxRate":"<0.1%","splitSumBoxInfo":"7.50\u4ebf","sumBoxInfo":"7.50\u4ebf","viewInfo":"0.0","viewInfoV2":"822"},{"avgSeatView":"99.5%","avgShowView":"104","avgViewBox":"30.0","boxInfo":"2.48","boxRate":"<0.1%","movieId":13511,"movieName":"\u5fcd\u8005\u795e\u9f9f2\uff1a\u7834\u5f71\u800c\u51fa","myRefundNumInfo":"--","myRefundRateInfo":"--","onlineBoxRate":"--","refundViewInfo":"1","refundViewRate":"0.1%","releaseInfo":"2016-07","releaseInfoColor":"#666666 1.00","seatRate":"<0.1%","showInfo":"8","showRate":"<0.1%","splitAvgViewBox":"30.0","splitBoxInfo":"2.48","splitBoxRate":"<0.1%","splitSumBoxInfo":"3.92\u4ebf","sumBoxInfo":"3.92\u4ebf","viewInfo":"0.0","viewInfoV2":"828"},{"avgSeatView":"6.2%","avgShowView":"4","avgViewBox":"30.0","boxInfo":"2.48","boxRate":"<0.1%","movieId":247086,"movieName":"\u795e\u79d8\u5bb6\u65cf","myRefundNumInfo":"4","myRefundRateInfo":"3.0%","onlineBoxRate":"--","refundViewInfo":"8","refundViewRate":"0.9%","releaseInfo":"\u4e0a\u662010\u5929","releaseInfoColor":"#666666 1.00","seatRate":"<0.1%","showInfo":"222","showRate":"<0.1%","splitAvgViewBox":"28.4","splitBoxInfo":"2.35","splitBoxRate":"<0.1%","splitSumBoxInfo":"1382.7\u4e07","sumBoxInfo":"1473.1\u4e07","viewInfo":"0.0","viewInfoV2":"828"},{"avgSeatView":"98.1%","avgShowView":"103","avgViewBox":"30.0","boxInfo":"2.45","boxRate":"<0.1%","movieId":246375,"movieName":"\u72ec\u7acb\u65e5\uff1a\u5377\u571f\u91cd\u6765","myRefundNumInfo":"--","myRefundRateInfo":"--","onlineBoxRate":"--","refundViewInfo":"0","refundViewRate":"<0.1%","releaseInfo":"2016-06","releaseInfoColor":"#666666 1.00","seatRate":"<0.1%","showInfo":"8","showRate":"<0.1%","splitAvgViewBox":"30.0","splitBoxInfo":"2.45","splitBoxRate":"<0.1%","splitSumBoxInfo":"5.02\u4ebf","sumBoxInfo":"5.02\u4ebf","viewInfo":"0.0","viewInfoV2":"817"},{"avgSeatView":"90.3%","avgShowView":"97","avgViewBox":"29.6","boxInfo":"2.27","boxRate":"<0.1%","movieId":249875,"movieName":"\u8c0d\u5f71\u91cd\u91cd5","myRefundNumInfo":"--","myRefundRateInfo":"--","onlineBoxRate":"--","refundViewInfo":"0","refundViewRate":"<0.1%","releaseInfo":"2016-08","releaseInfoColor":"#666666 1.00","seatRate":"<0.1%","showInfo":"8","showRate":"<0.1%","splitAvgViewBox":"29.6","splitBoxInfo":"2.27","splitBoxRate":"<0.1%","splitSumBoxInfo":"4.46\u4ebf","sumBoxInfo":"4.46\u4ebf","viewInfo":"0.0","viewInfoV2":"769"},{"avgSeatView":"95.0%","avgShowView":"104","avgViewBox":"30.2","boxInfo":"2.19","boxRate":"<0.1%","movieId":246591,"movieName":"\u5927\u9c7c\u6d77\u68e0","myRefundNumInfo":"--","myRefundRateInfo":"--","onlineBoxRate":"--","refundViewInfo":"218","refundViewRate":"23.1%","releaseInfo":"2016-07","releaseInfoColor":"#666666 1.00","seatRate":"<0.1%","showInfo":"7","showRate":"<0.1%","splitAvgViewBox":"30.2","splitBoxInfo":"2.19","splitBoxRate":"<0.1%","splitSumBoxInfo":"5.63\u4ebf","sumBoxInfo":"5.63\u4ebf","viewInfo":"0.0","viewInfoV2":"725"},{"avgSeatView":"90.5%","avgShowView":"80","avgViewBox":"30.1","boxInfo":"2.16","boxRate":"<0.1%","movieId":78637,"movieName":"\u51b0\u5ddd\u65f6\u4ee35\uff1a\u661f\u9645\u78b0\u649e","myRefundNumInfo":"--","myRefundRateInfo":"--","onlineBoxRate":"--","refundViewInfo":"0","refundViewRate":"<0.1%","releaseInfo":"2016-08","releaseInfoColor":"#666666 1.00","seatRate":"<0.1%","showInfo":"9","showRate":"<0.1%","splitAvgViewBox":"30.1","splitBoxInfo":"2.16","splitBoxRate":"<0.1%","splitSumBoxInfo":"4.46\u4ebf","sumBoxInfo":"4.46\u4ebf","viewInfo":"0.0","viewInfoV2":"717"},{"avgSeatView":"49.2%","avgShowView":"33","avgViewBox":"26.5","boxInfo":"2.14","boxRate":"<0.1%","movieId":368089,"movieName":"\u548c\u7530\u7389\u4f20\u5947","myRefundNumInfo":"0","myRefundRateInfo":"<0.1%","onlineBoxRate":"--","refundViewInfo":"1","refundViewRate":"0.1%","releaseInfo":"\u4e0a\u66206\u5929","releaseInfoColor":"#666666 1.00","seatRate":"<0.1%","showInfo":"25","showRate":"<0.1%","splitAvgViewBox":"26.3","splitBoxInfo":"2.12","splitBoxRate":"<0.1%","splitSumBoxInfo":"64.2\u4e07","sumBoxInfo":"66.5\u4e07","viewInfo":"0.0","viewInfoV2":"808"},{"avgSeatView":"12.5%","avgShowView":"7","avgViewBox":"39.3","boxInfo":"1.89","boxRate":"<0.1%","movieId":343012,"movieName":"\u5acc\u7591\u4ebax\u7684\u732e\u8eab","myRefundNumInfo":"6","myRefundRateInfo":"4.0%","onlineBoxRate":"--","refundViewInfo":"6","refundViewRate":"1.2%","releaseInfo":"\u4e0a\u662031\u5929","releaseInfoColor":"#666666 1.00","seatRate":"<0.1%","showInfo":"74","showRate":"<0.1%","splitAvgViewBox":"37.1","splitBoxInfo":"1.79","splitBoxRate":"<0.1%","splitSumBoxInfo":"3.78\u4ebf","sumBoxInfo":"4.01\u4ebf","viewInfo":"0.0","viewInfoV2":"482"},{"avgSeatView":"93.2%","avgShowView":"93","avgViewBox":"30.2","boxInfo":"1.68","boxRate":"<0.1%","movieId":346478,"movieName":"\u795e\u79d8\u4e16\u754c\u5386\u9669\u8bb03","myRefundNumInfo":"--","myRefundRateInfo":"--","onlineBoxRate":"--","refundViewInfo":"0","refundViewRate":"<0.1%","releaseInfo":"2016-07","releaseInfoColor":"#666666 1.00","seatRate":"<0.1%","showInfo":"6","showRate":"<0.1%","splitAvgViewBox":"30.2","splitBoxInfo":"1.68","splitBoxRate":"<0.1%","splitSumBoxInfo":"6536.9\u4e07","sumBoxInfo":"6536.9\u4e07","viewInfo":"0.0","viewInfoV2":"556"},{"avgSeatView":"88.5%","avgShowView":"92","avgViewBox":"30.0","boxInfo":"1.65","boxRate":"<0.1%","movieId":246461,"movieName":"\u661f\u9645\u8ff7\u822a3\uff1a\u8d85\u8d8a\u661f\u8fb0","myRefundNumInfo":"--","myRefundRateInfo":"--","onlineBoxRate":"--","refundViewInfo":"0","refundViewRate":"<0.1%","releaseInfo":"2016-09","releaseInfoColor":"#666666 1.00","seatRate":"<0.1%","showInfo":"6","showRate":"<0.1%","splitAvgViewBox":"30.0","splitBoxInfo":"1.65","splitBoxRate":"<0.1%","splitSumBoxInfo":"4.40\u4ebf","sumBoxInfo":"4.40\u4ebf","viewInfo":"0.0","viewInfoV2":"550"},{"avgSeatView":"89.0%","avgShowView":"93","avgViewBox":"28.4","boxInfo":"1.57","boxRate":"<0.1%","movieId":248680,"movieName":"\u7231\u4e3d\u4e1d\u68a6\u6e38\u4ed9\u58832\uff1a\u955c\u4e2d\u5947\u9047\u8bb0","myRefundNumInfo":"--","myRefundRateInfo":"--","onlineBoxRate":"--","refundViewInfo":"0","refundViewRate":"<0.1%","releaseInfo":"2016-05","releaseInfoColor":"#666666 1.00","seatRate":"<0.1%","showInfo":"6","showRate":"<0.1%","splitAvgViewBox":"28.4","splitBoxInfo":"1.57","splitBoxRate":"<0.1%","splitSumBoxInfo":"3.86\u4ebf","sumBoxInfo":"3.86\u4ebf","viewInfo":"0.0","viewInfoV2":"553"},{"avgSeatView":"92.4%","avgShowView":"101","avgViewBox":"29.9","boxInfo":"1.51","boxRate":"<0.1%","movieId":248918,"movieName":"\u795e\u5947\u52a8\u7269\u5728\u54ea\u91cc","myRefundNumInfo":"--","myRefundRateInfo":"--","onlineBoxRate":"--","refundViewInfo":"0","refundViewRate":"<0.1%","releaseInfo":"2016-11","releaseInfoColor":"#666666 1.00","seatRate":"<0.1%","showInfo":"5","showRate":"<0.1%","splitAvgViewBox":"29.9","splitBoxInfo":"1.51","splitBoxRate":"<0.1%","splitSumBoxInfo":"5.90\u4ebf","sumBoxInfo":"5.90\u4ebf","viewInfo":"0.0","viewInfoV2":"504"},{"avgSeatView":"22.1%","avgShowView":"14","avgViewBox":"38.9","boxInfo":"1.33","boxRate":"<0.1%","movieId":605624,"movieName":"\u4e00\u5ff5\u65e0\u660e","myRefundNumInfo":"4","myRefundRateInfo":"5.9%","onlineBoxRate":"--","refundViewInfo":"5","refundViewRate":"1.4%","releaseInfo":"\u4e0a\u662024\u5929","releaseInfoColor":"#666666 1.00","seatRate":"<0.1%","showInfo":"25","showRate":"<0.1%","splitAvgViewBox":"36.1","splitBoxInfo":"1.24","splitBoxRate":"<0.1%","splitSumBoxInfo":"870.0\u4e07","sumBoxInfo":"936.3\u4e07","viewInfo":"0.0","viewInfoV2":"343"},{"avgSeatView":"7.5%","avgShowView":"5","avgViewBox":"32.7","boxInfo":"1.31","boxRate":"<0.1%","movieId":346460,"movieName":"\u51b0\u96ea\u5927\u4f5c\u6218","myRefundNumInfo":"5","myRefundRateInfo":"5.5%","onlineBoxRate":"--","refundViewInfo":"8","refundViewRate":"1.9%","releaseInfo":"\u4e0a\u662030\u5929","releaseInfoColor":"#666666 1.00","seatRate":"<0.1%","showInfo":"87","showRate":"<0.1%","splitAvgViewBox":"31.0","splitBoxInfo":"1.25","splitBoxRate":"<0.1%","splitSumBoxInfo":"4098.3\u4e07","sumBoxInfo":"4317.0\u4e07","viewInfo":"0.0","viewInfoV2":"403"},{"avgSeatView":"93.8%","avgShowView":"98","avgViewBox":"25.2","boxInfo":"1.23","boxRate":"<0.1%","movieId":672356,"movieName":"\u65b0\u5927\u5934\u513f\u5b50\u548c\u5c0f\u5934\u7238\u72382\u4e00\u65e5\u6210\u624d","myRefundNumInfo":"--","myRefundRateInfo":"--","onlineBoxRate":"--","refundViewInfo":"0","refundViewRate":"<0.1%","releaseInfo":"2016-08","releaseInfoColor":"#666666 1.00","seatRate":"<0.1%","showInfo":"5","showRate":"<0.1%","splitAvgViewBox":"25.2","splitBoxInfo":"1.23","splitBoxRate":"<0.1%","splitSumBoxInfo":"9003.1\u4e07","sumBoxInfo":"9003.1\u4e07","viewInfo":"0.0","viewInfoV2":"488"},{"avgSeatView":"10.5%","avgShowView":"12","avgViewBox":"26.3","boxInfo":"1.17","boxRate":"<0.1%","movieId":2101,"movieName":"\u53d8\u8138","myRefundNumInfo":"--","myRefundRateInfo":"--","onlineBoxRate":"--","refundViewInfo":"11","refundViewRate":"2.3%","releaseInfo":"1995-06","releaseInfoColor":"#666666 1.00","seatRate":"<0.1%","showInfo":"40","showRate":"<0.1%","splitAvgViewBox":"24.2","splitBoxInfo":"1.08","splitBoxRate":"<0.1%","splitSumBoxInfo":"2.7\u4e07","sumBoxInfo":"2.9\u4e07","viewInfo":"0.0","viewInfoV2":"448"}],"queryDate":"2017-04-30","serverTime":"2020-03-14 00:33:57","serverTimestamp":1584117237000,"splitTotalBox":"27240.4","splitTotalBoxInfo":"27240.4","splitTotalBoxUnit":"\u4e07","splitTotalBoxUnitInfo":"\u4e07","totalBox":"28879.9","totalBoxInfo":"28879.9","totalBoxUnit":"\u4e07","totalBoxUnitInfo":"\u4e07","updateInfo":"\u5317\u4eac\u65f6\u95f4\u6bcf\u592912\u70b9\u66f4\u65b0\u7968\u623f"},"status":{"crystal":200,"holidays":200,"list":200,"queryDate":200,"serverTime":200,"serverTimestamp":200,"splitTotalBox":200,"splitTotalBoxInfo":200,"splitTotalBoxUnit":200,"splitTotalBoxUnitInfo":200,"totalBox":200,"totalBoxInfo":200,"totalBoxUnit":200,"totalBoxUnitInfo":200,"updateInfo":200}}