{"success":{"crystal":true,"holidays":true,"list":true,"queryDate":true,"serverTime":true,"serverTimestamp":true,"splitTotalBox":true,"splitTotalBoxInfo":true,"splitTotalBoxUnit":true,"splitTotalBoxUnitInfo":true,"totalBox":true,"totalBoxInfo":true,"totalBoxUnit":true,"totalBoxUnitInfo":true,"updateInfo":true},"data":{"crystal":{"maoyanViewInfo":"201.1","onlineViewInfo":"326.0","status":2,"viewInfo":"379.3","viewUnitInfo":"\u4e07\u5f20"},"holidays":"","list":[{"avgSeatView":"7.9%","avgShowView":"12","avgViewBox":"35.4","boxInfo":"4979.91","boxRate":"37.4%","movieId":1189879,"movieName":"\u72ee\u5b50\u738b","myRefundNumInfo":"9770","myRefundRateInfo":"1.4%","onlineBoxRate":"87.9%","refundViewInfo":"2.2\u4e07","refundViewRate":"1.5%","releaseInfo":"\u4e0a\u66204\u5929","releaseInfoColor":"#666666 1.00","seatRate":"41.3%","showInfo":"118629","showRate":"33.6%","splitAvgViewBox":"32.5","splitBoxInfo":"4578.00","splitBoxRate":"37.4%","splitSumBoxInfo":"3.96\u4ebf","sumBoxInfo":"4.25\u4ebf","viewInfo":"140.4","viewInfoV2":"140.4\u4e07"},{"avgSeatView":"10.7%","avgShowView":"13","avgViewBox":"36.2","boxInfo":"4270.20","boxRate":"32.1%","movieId":1218141,"movieName":"\u626b\u6bd22\u5929\u5730\u5bf9\u51b3","myRefundNumInfo":"7011","myRefundRateInfo":"1.0%","onlineBoxRate":"87.2%","refundViewInfo":"1.4\u4e07","refundViewRate":"1.1%","releaseInfo":"\u4e0a\u662011\u5929","releaseInfoColor":"#666666 1.00","seatRate":"25.6%","showInfo":"92023","showRate":"26.0%","splitAvgViewBox":"33.4","splitBoxInfo":"3942.50","splitBoxRate":"32.2%","splitSumBoxInfo":"9.29\u4ebf","sumBoxInfo":"10.06\u4ebf","viewInfo":"117.8","viewInfoV2":"117.8\u4e07"},{"avgSeatView":"18.4%","avgShowView":"22","avgViewBox":"34.2","boxInfo":"1800.91","boxRate":"13.5%","movieId":1229534,"movieName":"\u94f6\u6cb3\u8865\u4e60\u73ed","myRefundNumInfo":"--","myRefundRateInfo":"--","onlineBoxRate":"89.0%","refundViewInfo":"--","refundViewRate":"--","releaseInfo":"\u70b9\u6620","releaseInfoColor":"#FF9900 1.00","seatRate":"6.6%","showInfo":"24373","showRate":"6.9%","splitAvgViewBox":"31.5","splitBoxInfo":"1658.23","splitBoxRate":"13.5%","splitSumBoxInfo":"5398.1\u4e07","sumBoxInfo":"5675.3\u4e07","viewInfo":"52.5","viewInfoV2":"52.5\u4e07"},{"avgSeatView":"8.2%","avgShowView":"9","avgViewBox":"33.4","boxInfo":"1151.31","boxRate":"8.6%","movieId":1198925,"movieName":"\u8718\u86db\u4fa0\uff1a\u82f1\u96c4\u8fdc\u5f81","myRefundNumInfo":"2507","myRefundRateInfo":"1.3%","onlineBoxRate":"86.8%","refundViewInfo":"5869","refundViewRate":"1.6%","releaseInfo":"\u4e0a\u662018\u5929","releaseInfoColor":"#666666 1.00","seatRate":"9.8%","showInfo":"39758","showRate":"11.2%","splitAvgViewBox":"30.5","splitBoxInfo":"1050.67","splitBoxRate":"8.5%","splitSumBoxInfo":"12.34\u4ebf","sumBoxInfo":"13.37\u4ebf","viewInfo":"34.4","viewInfoV2":"34.4\u4e07"},{"avgSeatView":"6.8%","avgShowView":"7","avgViewBox":"32.7","boxInfo":"309.50","boxRate":"2.3%","movieId":1211345,"movieName":"\u7231\u5ba0\u5927\u673a\u5bc62","myRefundNumInfo":"757","myRefundRateInfo":"1.4%","onlineBoxRate":"88.1%","refundViewInfo":"2267","refundViewRate":"2.3%","releaseInfo":"\u4e0a\u662011\u5929","releaseInfoColor":"#666666 1.00","seatRate":"3.2%","showInfo":"14389","showRate":"4.0%","splitAvgViewBox":"29.9","splitBoxInfo":"282.81","splitBoxRate":"2.3%","splitSumBoxInfo":"1.20\u4ebf","sumBoxInfo":"1.30\u4ebf","viewInfo":"9.4","viewInfoV2":"9.4\u4e07"},{"avgSeatView":"4.2%","avgShowView":"4","avgViewBox":"31.1","boxInfo":"197.07","boxRate":"1.4%","movieId":414997,"movieName":"\u547d\u8fd0\u4e4b\u591c\u2014\u2014\u5929\u4e4b\u676fII \uff1a\u8ff7\u5931\u4e4b\u8776","myRefundNumInfo":"514","myRefundRateInfo":"1.4%","onlineBoxRate":"91.3%","refundViewInfo":"1117","refundViewRate":"1.7%","releaseInfo":"\u4e0a\u66204\u5929","releaseInfoColor":"#666666 1.00","seatRate":"3.4%","showInfo":"16300","showRate":"4.6%","splitAvgViewBox":"28.0","splitBoxInfo":"177.06","splitBoxRate":"1.4%","splitSumBoxInfo":"2191.4\u4e07","sumBoxInfo":"2434.0\u4e07","viewInfo":"6.3","viewInfoV2":"6.3\u4e07"},{"avgSeatView":"6.8%","avgShowView":"7","avgViewBox":"30.4","boxInfo":"144.00","boxRate":"1.0%","movieId":1212,"movieName":"\u5343\u4e0e\u5343\u5bfb","myRefundNumInfo":"518","myRefundRateInfo":"1.8%","onlineBoxRate":"88.2%","refundViewInfo":"976","refundViewRate":"2.0%","releaseInfo":"\u4e0a\u662025\u5929","releaseInfoColor":"#666666 1.00","seatRate":"1.6%","showInfo":"7803","showRate":"2.2%","splitAvgViewBox":"27.5","splitBoxInfo":"130.22","splitBoxRate":"1.0%","splitSumBoxInfo":"4.38\u4ebf","sumBoxInfo":"4.81\u4ebf","viewInfo":"4.7","viewInfoV2":"4.7\u4e07"},{"avgSeatView":"1.8%","avgShowView":"2","avgViewBox":"34.1","boxInfo":"80.78","boxRate":"0.6%","movieId":1213262,"movieName":"\u7d20\u4eba\u7279\u5de5","myRefundNumInfo":"137","myRefundRateInfo":"1.2%","onlineBoxRate":"79.4%","refundViewInfo":"495","refundViewRate":"2.0%","releaseInfo":"\u4e0a\u66204\u5929","releaseInfoColor":"#666666 1.00","seatRate":"2.9%","showInfo":"13812","showRate":"3.9%","splitAvgViewBox":"31.6","splitBoxInfo":"74.85","splitBoxRate":"0.6%","splitSumBoxInfo":"1939.7\u4e07","sumBoxInfo":"2106.6\u4e07","viewInfo":"2.3","viewInfoV2":"2.3\u4e07"},{"avgSeatView":"6.4%","avgShowView":"6","avgViewBox":"27.7","boxInfo":"70.08","boxRate":"0.5%","movieId":1211698,"movieName":"\u789f\u4ed9","myRefundNumInfo":"354","myRefundRateInfo":"1.9%","onlineBoxRate":"90.4%","refundViewInfo":"597","refundViewRate":"2.3%","releaseInfo":"\u4e0a\u662025\u5929","releaseInfoColor":"#666666 1.00","seatRate":"0.9%","showInfo":"4554","showRate":"1.2%","splitAvgViewBox":"24.9","splitBoxInfo":"63.00","splitBoxRate":"0.5%","splitSumBoxInfo":"4648.5\u4e07","sumBoxInfo":"5139.0\u4e07","viewInfo":"2.5","viewInfoV2":"2.5\u4e07"},{"avgSeatView":"2.4%","avgShowView":"3","avgViewBox":"32.4","boxInfo":"46.93","boxRate":"0.3%","movieId":1230509,"movieName":"\u673a\u52a8\u6218\u58eb\u9ad8\u8fbeNT","myRefundNumInfo":"114","myRefundRateInfo":"1.7%","onlineBoxRate":"90.5%","refundViewInfo":"282","refundViewRate":"1.9%","releaseInfo":"\u4e0a\u66204\u5929","releaseInfoColor":"#666666 1.00","seatRate":"1.3%","showInfo":"6264","showRate":"1.7%","splitAvgViewBox":"29.0","splitBoxInfo":"42.13","splitBoxRate":"0.3%","splitSumBoxInfo":"665.2\u4e07","sumBoxInfo":"727.9\u4e07","viewInfo":"1.4","viewInfoV2":"1.4\u4e07"},{"avgSeatView":"3.5%","avgShowView":"4","avgViewBox":"30.0","boxInfo":"39.20","boxRate":"0.2%","movieId":1234461,"movieName":"\u732a\u732a\u4fa0\u00b7\u4e0d\u53ef\u601d\u8bae\u7684\u4e16\u754c","myRefundNumInfo":"90","myRefundRateInfo":"1.4%","onlineBoxRate":"82.2%","refundViewInfo":"367","refundViewRate":"2.7%","releaseInfo":"\u4e0a\u662011\u5929","releaseInfoColor":"#666666 1.00","seatRate":"0.8%","showInfo":"4114","showRate":"1.1%","splitAvgViewBox":"27.5","splitBoxInfo":"35.96","splitBoxRate":"0.2%","splitSumBoxInfo":"2883.1\u4e07","sumBoxInfo":"3100.0\u4e07","viewInfo":"1.3","viewInfoV2":"1.3\u4e07"},{"avgSeatView":"5.4%","avgShowView":"5","avgViewBox":"36.7","boxInfo":"28.00","boxRate":"0.2%","movieId":246264,"movieName":"\u73a9\u5177\u603b\u52a8\u54584","myRefundNumInfo":"67","myRefundRateInfo":"1.7%","onlineBoxRate":"86.5%","refundViewInfo":"110","refundViewRate":"1.4%","releaseInfo":"\u4e0a\u662025\u5929","releaseInfoColor":"#666666 1.00","seatRate":"0.3%","showInfo":"1569","showRate":"0.4%","splitAvgViewBox":"33.7","splitBoxInfo":"25.67","splitBoxRate":"0.2%","splitSumBoxInfo":"1.83\u4ebf","sumBoxInfo":"1.99\u4ebf","viewInfo":"0.7","viewInfoV2":"7612"},{"avgSeatView":"30.8%","avgShowView":"27","avgViewBox":"31.1","boxInfo":"13.86","boxRate":"0.1%","movieId":1234382,"movieName":"\u5468\u6069\u6765\u56de\u5ef6\u5b89","myRefundNumInfo":"2","myRefundRateInfo":"2.3%","onlineBoxRate":"16.3%","refundViewInfo":"68","refundViewRate":"1.5%","releaseInfo":"\u4e0a\u662062\u5929","releaseInfoColor":"#666666 1.00","seatRate":"<0.1%","showInfo":"169","showRate":"<0.1%","splitAvgViewBox":"30.9","splitBoxInfo":"13.77","splitBoxRate":"0.1%","splitSumBoxInfo":"2326.6\u4e07","sumBoxInfo":"2344.2\u4e07","viewInfo":"0.4","viewInfoV2":"4451"},{"avgSeatView":"22.2%","avgShowView":"18","avgViewBox":"27.4","boxInfo":"12.62","boxRate":"<0.1%","movieId":1262593,"movieName":"\u516b\u5b50","myRefundNumInfo":"20","myRefundRateInfo":"8.8%","onlineBoxRate":"13.6%","refundViewInfo":"224","refundViewRate":"4.6%","releaseInfo":"\u4e0a\u662025\u5929","releaseInfoColor":"#666666 1.00","seatRate":"<0.1%","showInfo":"269","showRate":"<0.1%","splitAvgViewBox":"27.1","splitBoxInfo":"12.51","splitBoxRate":"0.1%","splitSumBoxInfo":"1787.6\u4e07","sumBoxInfo":"1850.7\u4e07","viewInfo":"0.4","viewInfoV2":"4606"},{"avgSeatView":"100%","avgShowView":"123","avgViewBox":"39.3","boxInfo":"10.14","boxRate":"<0.1%","movieId":1239678,"movieName":"\u539f\u6765\u5982\u6b64","myRefundNumInfo":"--","myRefundRateInfo":"--","onlineBoxRate":"4.8%","refundViewInfo":"0","refundViewRate":"<0.1%","releaseInfo":"\u4e0a\u662095\u5929","releaseInfoColor":"#666666 1.00","seatRate":"<0.1%","showInfo":"21","showRate":"<0.1%","splitAvgViewBox":"37.4","splitBoxInfo":"9.65","splitBoxRate":"<0.1%","splitSumBoxInfo":"374.3\u4e07","sumBoxInfo":"394.3\u4e07","viewInfo":"0.2","viewInfoV2":"2580"},{"avgSeatView":"5.2%","avgShowView":"5","avgViewBox":"31.4","boxInfo":"8.42","boxRate":"<0.1%","movieId":246061,"movieName":"\u54e5\u65af\u62c92\uff1a\u602a\u517d\u4e4b\u738b","myRefundNumInfo":"31","myRefundRateInfo":"1.8%","onlineBoxRate":"87.8%","refundViewInfo":"367","refundViewRate":"12.0%","releaseInfo":"\u4e0a\u662046\u5929","releaseInfoColor":"#666666 1.00","seatRate":"0.1%","showInfo":"636","showRate":"0.1%","splitAvgViewBox":"28.8","splitBoxInfo":"7.73","splitBoxRate":"<0.1%","splitSumBoxInfo":"8.66\u4ebf","sumBoxInfo":"9.36\u4ebf","viewInfo":"0.2","viewInfoV2":"2680"},{"avgSeatView":"--","avgShowView":"56","avgViewBox":"29.4","boxInfo":"8.24","boxRate":"<0.1%","movieId":836,"movieName":"\u6bd5\u4e1a\u90a3\u5e74","myRefundNumInfo":"--","myRefundRateInfo":"--","onlineBoxRate":"63.0%","refundViewInfo":"0","refundViewRate":"<0.1%","releaseInfo":"2012-09","releaseInfoColor":"#666666 1.00","seatRate":"<0.1%","showInfo":"50","showRate":"<0.1%","splitAvgViewBox":"29.1","splitBoxInfo":"8.16","splitBoxRate":"<0.1%","splitSumBoxInfo":"1403.3\u4e07","sumBoxInfo":"1406.0\u4e07","viewInfo":"0.2","viewInfoV2":"2799"},{"avgSeatView":"1.5%","avgShowView":"2","avgViewBox":"24.9","boxInfo":"7.76","boxRate":"<0.1%","movieId":1235560,"movieName":"\u767d\u86c7\uff1a\u7f18\u8d77","myRefundNumInfo":"39","myRefundRateInfo":"3.0%","onlineBoxRate":"44.7%","refundViewInfo":"59","refundViewRate":"1.8%","releaseInfo":"2019-01","releaseInfoColor":"#666666 1.00","seatRate":"0.4%","showInfo":"2113","showRate":"0.5%","splitAvgViewBox":"23.1","splitBoxInfo":"7.21","splitBoxRate":"<0.1%","splitSumBoxInfo":"4.14\u4ebf","sumBoxInfo":"4.52\u4ebf","viewInfo":"0.3","viewInfoV2":"3116"},{"avgSeatView":"--","avgShowView":"79","avgViewBox":"50.0","boxInfo":"5.86","boxRate":"<0.1%","movieId":1184988,"movieName":"\u661f\u6708\u591c","myRefundNumInfo":"--","myRefundRateInfo":"--","onlineBoxRate":"<0.1%","refundViewInfo":"0","refundViewRate":"<0.1%","releaseInfo":"\u4e0a\u662018\u5929","releaseInfoColor":"#666666 1.00","seatRate":"<0.1%","showInfo":"15","showRate":"<0.1%","splitAvgViewBox":"50.0","splitBoxInfo":"5.86","splitBoxRate":"<0.1%","splitSumBoxInfo":"201.3\u4e07","sumBoxInfo":"201.4\u4e07","viewInfo":"0.1","viewInfoV2":"1172"},{"avgSeatView":"6.0%","avgShowView":"5","avgViewBox":"30.8","boxInfo":"5.37","boxRate":"<0.1%","movieId":1204589,"movieName":"\u7edd\u6740\u6155\u5c3c\u9ed1","myRefundNumInfo":"8","myRefundRateInfo":"1.1%","onlineBoxRate":"75.6%","refundViewInfo":"832","refundViewRate":"32.3%","releaseInfo":"\u4e0a\u662033\u5929","releaseInfoColor":"#666666 1.00","seatRate":"<0.1%","showInfo":"360","showRate":"0.1%","splitAvgViewBox":"28.2","splitBoxInfo":"4.91","splitBoxRate":"<0.1%","splitSumBoxInfo":"8268.3\u4e07","sumBoxInfo":"9140.3\u4e07","viewInfo":"0.1","viewInfoV2":"1743"},{"avgSeatView":"--","avgShowView":"23","avgViewBox":"32.2","boxInfo":"5.17","boxRate":"<0.1%","movieId":643506,"movieName":"\u53e4\u9547\u753b\u60c5","myRefundNumInfo":"--","myRefundRateInfo":"--","onlineBoxRate":"51.6%","refundViewInfo":"0","refundViewRate":"<0.1%","releaseInfo":"\u5c55\u6620","releaseInfoColor":"#666666 1.00","seatRate":"<0.1%","showInfo":"70","showRate":"<0.1%","splitAvgViewBox":"32.1","splitBoxInfo":"5.16","splitBoxRate":"<0.1%","splitSumBoxInfo":"1546.3\u4e07","sumBoxInfo":"1549.8\u4e07","viewInfo":"0.1","viewInfoV2":"1605"},{"avgSeatView":"87.5%","avgShowView":"57","avgViewBox":"34.3","boxInfo":"5.03","boxRate":"<0.1%","movieId":1206829,"movieName":"\u97f3\u4e50\u5bb6","myRefundNumInfo":"1","myRefundRateInfo":"10.0%","onlineBoxRate":"4.1%","refundViewInfo":"1","refundViewRate":"<0.1%","releaseInfo":"\u4e0a\u662060\u5929","releaseInfoColor":"#666666 1.00","seatRate":"<0.1%","showInfo":"26","showRate":"<0.1%","splitAvgViewBox":"34.3","splitBoxInfo":"5.03","splitBoxRate":"<0.1%","splitSumBoxInfo":"410.5\u4e07","sumBoxInfo":"417.9\u4e07","viewInfo":"0.1","viewInfoV2":"1465"},{"avgSeatView":"3.4%","avgShowView":"3","avgViewBox":"30.5","boxInfo":"4.68","boxRate":"<0.1%","movieId":1242431,"movieName":"\u6700\u597d\u7684\u6211\u4eec","myRefundNumInfo":"40","myRefundRateInfo":"4.0%","onlineBoxRate":"81.4%","refundViewInfo":"55","refundViewRate":"3.4%","releaseInfo":"\u4e0a\u662040\u5929","releaseInfoColor":"#666666 1.00","seatRate":"0.1%","showInfo":"607","showRate":"0.1%","splitAvgViewBox":"28.2","splitBoxInfo":"4.32","splitBoxRate":"<0.1%","splitSumBoxInfo":"3.83\u4ebf","sumBoxInfo":"4.16\u4ebf","viewInfo":"0.1","viewInfoV2":"1534"},{"avgSeatView":"55.0%","avgShowView":"52","avgViewBox":"54.8","boxInfo":"4.55","boxRate":"<0.1%","movieId":1277746,"movieName":"\u6b66\u9675\u5c71\u4e0a\u7684\u661f\u5149","myRefundNumInfo":"--","myRefundRateInfo":"--","onlineBoxRate":"8.1%","refundViewInfo":"11","refundViewRate":"1.3%","releaseInfo":"\u4e0a\u662059\u5929","releaseInfoColor":"#666666 1.00","seatRate":"<0.1%","showInfo":"16","showRate":"<0.1%","splitAvgViewBox":"54.8","splitBoxInfo":"4.55","splitBoxRate":"<0.1%","splitSumBoxInfo":"729.1\u4e07","sumBoxInfo":"729.5\u4e07","viewInfo":"0.0","viewInfoV2":"831"},{"avgSeatView":"100%","avgShowView":"20","avgViewBox":"27.4","boxInfo":"4.46","boxRate":"<0.1%","movieId":330115,"movieName":"\u6211\u548c\u795e\u9a6c\u67e5\u5e72","myRefundNumInfo":"--","myRefundRateInfo":"--","onlineBoxRate":"92.0%","refundViewInfo":"2","refundViewRate":"0.1%","releaseInfo":"2012-12","releaseInfoColor":"#666666 1.00","seatRate":"<0.1%","showInfo":"83","showRate":"<0.1%","splitAvgViewBox":"27.0","splitBoxInfo":"4.40","splitBoxRate":"<0.1%","splitSumBoxInfo":"3250.0\u4e07","sumBoxInfo":"3262.4\u4e07","viewInfo":"0.1","viewInfoV2":"1628"},{"avgSeatView":"--","avgShowView":"100","avgViewBox":"60.0","boxInfo":"4.20","boxRate":"<0.1%","movieId":319904,"movieName":"\u76db\u4e16\u79e7\u6b4c","myRefundNumInfo":"--","myRefundRateInfo":"--","onlineBoxRate":"<0.1%","refundViewInfo":"0","refundViewRate":"<0.1%","releaseInfo":"\u5c55\u6620","releaseInfoColor":"#666666 1.00","seatRate":"<0.1%","showInfo":"7","showRate":"<0.1%","splitAvgViewBox":"60.0","splitBoxInfo":"4.20","splitBoxRate":"<0.1%","splitSumBoxInfo":"1436.9\u4e07","sumBoxInfo":"1438.6\u4e07","viewInfo":"0.0","viewInfoV2":"700"},{"avgSeatView":"2.5%","avgShowView":"3","avgViewBox":"15.6","boxInfo":"2.28","boxRate":"<0.1%","movieId":1218727,"movieName":"\u4f55\u4ee5\u4e3a\u5bb6","myRefundNumInfo":"17","myRefundRateInfo":"2.4%","onlineBoxRate":"84.5%","refundViewInfo":"39","refundViewRate":"2.6%","releaseInfo":"\u4e0a\u662078\u5929","releaseInfoColor":"#666666 1.00","seatRate":"0.1%","showInfo":"606","showRate":"0.1%","splitAvgViewBox":"13.2","splitBoxInfo":"1.93","splitBoxRate":"<0.1%","splitSumBoxInfo":"3.41\u4ebf","sumBoxInfo":"3.74\u4ebf","viewInfo":"0.1","viewInfoV2":"1459"},{"avgSeatView":"1.4%","avgShowView":"2","avgViewBox":"17.2","boxInfo":"1.82","boxRate":"<0.1%","movieId":1204720,"movieName":"\u5988\u5988\u54aa\u9e2d","myRefundNumInfo":"13","myRefundRateInfo":"2.1%","onlineBoxRate":"84.4%","refundViewInfo":"24","refundViewRate":"2.2%","releaseInfo":"2018-03","releaseInfoColor":"#666666 1.00","seatRate":"0.1%","showInfo":"698","showRate":"0.1%","splitAvgViewBox":"14.7","splitBoxInfo":"1.56","splitBoxRate":"<0.1%","splitSumBoxInfo":"3501.1\u4e07","sumBoxInfo":"3734.5\u4e07","viewInfo":"0.1","viewInfoV2":"1058"},{"avgSeatView":"20.1%","avgShowView":"17","avgViewBox":"28.4","boxInfo":"1.65","boxRate":"<0.1%","movieId":1281621,"movieName":"\u82b1\u513f\u4e0e\u6b4c\u58f0","myRefundNumInfo":"1","myRefundRateInfo":"0.4%","onlineBoxRate":"70.7%","refundViewInfo":"12","refundViewRate":"2.0%","releaseInfo":"\u4e0a\u662046\u5929","releaseInfoColor":"#666666 1.00","seatRate":"<0.1%","showInfo":"35","showRate":"<0.1%","splitAvgViewBox":"26.5","splitBoxInfo":"1.54","splitBoxRate":"<0.1%","splitSumBoxInfo":"332.2\u4e07","sumBoxInfo":"335.4\u4e07","viewInfo":"0.0","viewInfoV2":"583"},{"avgSeatView":"100.0%","avgShowView":"164","avgViewBox":"30.2","boxInfo":"1.48","boxRate":"<0.1%","movieId":342568,"movieName":"\u8be1\u68a6\u51f6\u94c3","myRefundNumInfo":"--","myRefundRateInfo":"--","onlineBoxRate":"<0.1%","refundViewInfo":"0","refundViewRate":"<0.1%","releaseInfo":"2016-09","releaseInfoColor":"#666666 1.00","seatRate":"<0.1%","showInfo":"3","showRate":"<0.1%","splitAvgViewBox":"30.2","splitBoxInfo":"1.48","splitBoxRate":"<0.1%","splitSumBoxInfo":"1175.3\u4e07","sumBoxInfo":"1175.3\u4e07","viewInfo":"0.0","viewInfoV2":"490"},{"avgSeatView":"2.0%","avgShowView":"3","avgViewBox":"16.2","boxInfo":"1.48","boxRate":"<0.1%","movieId":1254277,"movieName":"\u4e00\u6761\u72d7\u7684\u4f7f\u547d2","myRefundNumInfo":"6","myRefundRateInfo":"1.3%","onlineBoxRate":"79.5%","refundViewInfo":"21","refundViewRate":"2.2%","releaseInfo":"\u4e0a\u662060\u5929","releaseInfoColor":"#666666 1.00","seatRate":"0.1%","showInfo":"430","showRate":"0.1%","splitAvgViewBox":"14.1","splitBoxInfo":"1.28","splitBoxRate":"<0.1%","splitSumBoxInfo":"1.79\u4ebf","sumBoxInfo":"1.96\u4ebf","viewInfo":"0.0","viewInfoV2":"910"},{"avgSeatView":"100%","avgShowView":"123","avgViewBox":"40.0","boxInfo":"1.47","boxRate":"<0.1%","movieId":1213186,"movieName":"\u9ec4\u73ab\u7470","myRefundNumInfo":"--","myRefundRateInfo":"--","onlineBoxRate":"<0.1%","refundViewInfo":"0","refundViewRate":"<0.1%","releaseInfo":"\u4e0a\u662052\u5929","releaseInfoColor":"#666666 1.00","seatRate":"<0.1%","showInfo":"3","showRate":"<0.1%","splitAvgViewBox":"40.0","splitBoxInfo":"1.47","splitBoxRate":"<0.1%","splitSumBoxInfo":"1102.4\u4e07","sumBoxInfo":"1102.4\u4e07","viewInfo":"0.0","viewInfoV2":"369"},{"avgSeatView":"70.6%","avgShowView":"66","avgViewBox":"28.3","boxInfo":"1.29","boxRate":"<0.1%","movieId":1236504,"movieName":"\u6b63\u6b63\u7684\u4e16\u754c","myRefundNumInfo":"--","myRefundRateInfo":"--","onlineBoxRate":"<0.1%","refundViewInfo":"0","refundViewRate":"<0.1%","releaseInfo":"2018-11","releaseInfoColor":"#666666 1.00","seatRate":"<0.1%","showInfo":"7","showRate":"<0.1%","splitAvgViewBox":"28.3","splitBoxInfo":"1.29","splitBoxRate":"<0.1%","splitSumBoxInfo":"41.4\u4e07","sumBoxInfo":"42.0\u4e07","viewInfo":"0.0","viewInfoV2":"457"},{"avgSeatView":"63.5%","avgShowView":"126","avgViewBox":"50.0","boxInfo":"1.25","boxRate":"<0.1%","movieId":1238775,"movieName":"\u7279\u522b\u8ffd\u8e2a","myRefundNumInfo":"--","myRefundRateInfo":"--","onlineBoxRate":"<0.1%","refundViewInfo":"50","refundViewRate":"16.6%","releaseInfo":"2018-09","releaseInfoColor":"#666666 1.00","seatRate":"<0.1%","showInfo":"2","showRate":"<0.1%","splitAvgViewBox":"50.0","splitBoxInfo":"1.25","splitBoxRate":"<0.1%","splitSumBoxInfo":"743.6\u4e07","sumBoxInfo":"743.8\u4e07","viewInfo":"0.0","viewInfoV2":"251"}],"queryDate":"2019-07-15","serverTime":"2020-03-14 00:39:16","serverTimestamp":1584117556000,"splitTotalBox":"12220.0","splitTotalBoxInfo":"12220.0","splitTotalBoxUnit":"\u4e07","splitTotalBoxUnitInfo":"\u4e07","totalBox":"13281.6","totalBoxInfo":"13281.6","totalBoxUnit":"\u4e07","totalBoxUnitInfo":"\u4e07","updateInfo":"\u5317\u4eac\u65f6\u95f4\u6bcf\u592912\u70b9\u66f4\u65b0\u7968\u623f"},"status":{"crystal":200,"holidays":200,"list":200,"queryDate":200,"serverTime":200,"serverTimestamp":200,"splitTotalBox":200,"splitTotalBoxInfo":200,"splitTotalBoxUnit":200,"splitTotalBoxUnitInfo":200,"totalBox":200,"totalBoxInfo":200,"totalBoxUnit":200,"totalBoxUnitInfo":200,"updateInfo":200}}